Workbook

Sheet JAN
C1: LOBBY ENTERPRISES
A2: PROPERTY MANAGERS AND ESTATE AGENTS
A3: JAN 2026
J4: P.O.BOX 11987
A5: STUDIO HAVEN | J5: TEL : 0722711933/4454322
A6: A/C | I6: Care taker | J6: ELIZABETH
I7: Phone no | J7: 0796292019
A8: HSE NO | B8: NAME | C8: PHONE NO | D8: DEPOSIT PAID | E8: MONTHLY RENT | F8: WATER BILL | G8: BAL B/D | H8: RENT DUE | I8: RENT PAID | J8: RCT NO | K8: DATE | L8: PERIOD | M8: BALANCE | N8: STATUS | O8: FORMS
A9: H1 | B9: ROSE | C9: 0707714065 | E9: 10100 | F9: 459 | H9: =D9+E9+G9+F9 -> 10559 | I9: =10559 -> 10559 | J9: UA4HM2SEQI | K9: 4TH JAN | L9: JAN | M9: =H9-I9 -> 0
A10: H2 | B10: BENSON | C10: 0741776284 | E10: 7100 | F10: 578 | H10: =D10+E10+G10+F10 -> 7678 | I10: =7678 -> 7678 | J10: UA9AY38T20 | K10: 9TH JAN | L10: JAN | M10: =H10-I10 -> 0
A11: H3 | B11: VACANT | H11: =D11+E11+G11+F11 -> 0 | L11: JAN | M11: =H11-I11 -> 0 | N11: locked
A12: H4 | B12: CECILIA | C12: 0743724464 | E12: 10100 | F12: 300 | H12: =D12+E12+G12+F12 -> 10400 | I12: =10627 -> 10627 | J12: UA60I2XQPE | L12: JAN | M12: =H12-I12 -> -227
A13: H5 | B13: PAUL | C13: 0723316248 | E13: 10100 | F13: 0 | H13: =D13+E13+G13+F13 -> 10100 | I13: =10100 -> 10100 | J13: UABOF3JIQB | L13: JAN | M13: =H13-I13 -> 0
A14: H6 | B14: EUGENE | C14: 0792983014 | E14: 10100 | F14: 1050 | H14: =D14+E14+G14+F14 -> 11150 | I14: =11205 -> 11205 | J14: DIRECT | L14: JAN | M14: =H14-I14 -> -55
A15: H7 | B15: JAMES | C15: 0713161165 | E15: 10100 | F15: 1200 | H15: =D15+E15+G15+F15 -> 11300 | I15: =11460 -> 11460 | J15: DIRECT | L15: JAN | M15: =H15-I15 -> -160
A16: H8 | B16: BONIFACE | C16: 0703962575 | E16: 12100 | F16: 289 | H16: =D16+E16+G16+F16 -> 12389 | I16: =12389 -> 12389 | J16: UAB2M3NP4G | K16: 11TH JAN | L16: JAN | M16: =H16-I16 -> 0
A17: H9 | B17: ROBERT | C17: 0726405930 | E17: 14100 | F17: 900 | H17: =D17+E17+G17+F17 -> 15000 | I17: =13000 -> 13000 | J17: UAE133QJE6 | L17: JAN | M17: =H17-I17 -> 2000
A18: H10 | B18: BEATRICE | C18: 0711729058 | E18: 10100 | F18: 450 | H18: =D18+E18+G18+F18 -> 10550 | I18: =10627 -> 10627 | J18: UA2RI2O2PD | K18: 2ND JAN | L18: JAN | M18: =H18-I18 -> -77
A19: H11 | B19: PETER GACHURI | C19: 0708568404 | E19: 9100 | F19: 150 | H19: =D19+E19+G19+F19 -> 9250 | L19: JAN | M19: =H19-I19 -> 9250
A20: H12 | B20: GIDEON | C20: 0712026963 | E20: 10100 | F20: 300 | H20: =D20+E20+G20+F20 -> 10400 | I20: =10400 -> 10400 | J20: UA6952X62K | K20: 6TH JAN | L20: JAN | M20: =H20-I20 -> 0
A21: H13 | B21: TREVOR | C21: 0716484383 | F21: 0 | H21: =D21+E21+G21+F21 -> 0 | L21: JAN | M21: =H21-I21 -> 0
A22: H14 | B22: LAWRENCE | C22: 0713605808 | E22: 10100 | F22: 0 | G22: 16000 | H22: =D22+E22+G22+F22 -> 26100 | I22: =9000+1000 -> 10000 | J22: UAHGB3UU03/UARGB4U965 | K22: 17TH/'26TH JAN | L22: JAN | M22: =H22-I22 -> 16100
A23: H15 | B23: NANCY | C23: 0715189007 | E23: 10100 | F23: 300 | H23: =D23+E23+G23+F23 -> 10400 | I23: =10525 -> 10525 | J23: UA5N02YEOZ | K23: 5TH JAN | L23: JAN | M23: =H23-I23 -> -125
A24: H16 | B24: KELVIN GITONGA | C24: 07792391382 | E24: 10100 | F24: 150 | H24: =D24+E24+G24+F24 -> 10250 | I24: =10355 -> 10355 | J24: UA5R42RC93 | L24: JAN | M24: =H24-I24 -> -105 | P24: CR | Q24: =I57/H57*100 -> 93.959017
A25: S1 | B25: VIVIAN | C25: 0748596476 | E25: 8500 | F25: 450 | H25: =D25+E25+G25+F25 -> 8950 | I25: 9076 | J25: DIRECT | L25: JAN | M25: =H25-I25 -> -126
A26: S2 | B26: LINDA | C26: 0748689851 | E26: 10100 | F26: 300 | H26: =D26+E26+G26+F26 -> 10400 | I26: 10270 | J26: UA55V2ZG6Q | L26: JAN | M26: =H26-I26 -> 130
A27: S3 | B27: WARREN | C27: 0769883948 | E27: 10100 | F27: 0 | H27: =D27+E27+G27+F27 -> 10100 | I27: =10780 -> 10780 | J27: UA59R2ZI3D | K27: 5TH JAN | L27: JAN | M27: =H27-I27 -> -680
A28: S4 | B28: SCOLA | C28: 0793889379 | E28: 9100 | F28: 289 | H28: =D28+E28+G28+F28 -> 9389 | I28: =9389 -> 9389 | J28: UA6HE31ARF | K28: 6TH JAN | L28: JAN | M28: =H28-I28 -> 0 | P28: CR | Q28: 75.570748
A29: S5 | B29: CARETAKER | H29: =D29+E29+G29+F29 -> 0
A30: S6 | B30: IMELDA | C30: 0723500330 | E30: 10100 | F30: 150 | H30: =D30+E30+G30+F30 -> 10250 | I30: =10270 -> 10270 | J30: UAAD33E8EJ | K30: 10TH JAN | L30: JAN | M30: =H30-I30 -> -20 | P30: 2 BROKEN PADLOCK ADD 1000
A31: S7 | B31: EVANS | C31: 0702377661 | E31: 10100 | F31: 60 | H31: =D31+E31+G31+F31 -> 10160 | I31: =8600+1568 -> 10168 | J31: TLPJ41UTT7/UA6J42VIKE | K31: 25TH DEC/6TH JAN | L31: JAN | M31: =H31-I31 -> -8
A32: S8 | B32: BRIAN CHERUIYOT | D32: 10000 | E32: 10100 | H32: =D32+E32+G32+F32 -> 20100 | I32: =20100 -> 20100 | J32: UA2B12QDUE | L32: JAN | M32: =H32-I32 -> 0
A33: S9 | B33: DORCAS | C33: 0723433108 | E33: 10100 | F33: 0 | H33: =D33+E33+G33+F33 -> 10100 | I33: =10270 -> 10270 | J33: UA9LR37RLY | K33: 9TH JAN | L33: JAN | M33: =H33-I33 -> -170
A34: S10 | B34: MONICAH | C34: 0740454928 | E34: 10100 | F34: 150 | H34: =D34+E34+G34+F34 -> 10250 | I34: =10270 -> 10270 | J34: UA2SG67O5R | K34: 2ND JAN | L34: JAN | M34: =H34-I34 -> -20
A35: S11 | B35: IAN KAMAU | C35: 0745292688 | E35: 10100 | F35: 0 | H35: =D35+E35+G35+F35 -> 10100 | I35: 10270 | J35: UA8MS385SJ | L35: JAN | M35: =H35-I35 -> -170
A36: S12 | B36: JUSTINE | C36: 0724282631 | E36: 10100 | F36: 0 | H36: =D36+E36+G36+F36 -> 10100 | I36: 10270 | J36: DIRECT | L36: JAN | M36: =H36-I36 -> -170
A37: S13 | B37: DERRICK | C37: 0707280087 | E37: 10100 | F37: 300 | H37: =D37+E37+G37+F37 -> 10400 | I37: =10440 -> 10440 | J37: UA5IA30U53 | K37: 5TH JAN | L37: JAN | M37: =H37-I37 -> -40
A38: S14 | B38: VINCENT | C38: 0798467289 | E38: 10100 | F38: 300 | H38: =D38+E38+G38+F38 -> 10400 | I38: =10400 -> 10400 | J38: TO CONFIRM | L38: JAN | M38: =H38-I38 -> 0
A39: S15 | B39: ARON | C39: 0706195266 | E39: 10100 | F39: 300 | H39: =D39+E39+G39+F39 -> 10400 | I39: =10440 -> 10440 | J39: UAA5Q3N1P3 | L39: JAN | M39: =H39-I39 -> -40
A40: S16 | B40: BEN SAKWA | C40: 0789232363 | E40: 1000 | H40: =D40+E40+G40+F40 -> 1000 | I40: =1000 -> 1000 | J40: UA8GC36XI4 | K40: 8TH JAN | L40: JAN | M40: =H40-I40 -> 0
A41: S17 | B41: VACANT | H41: =D41+E41+G41+F41 -> 0 | L41: JAN | M41: =H41-I41 -> 0
A42: S18 | B42: LIZZIE NYAMBURA | C42: 0792838695 | E42: 10100 | F42: 85 | H42: =D42+E42+G42+F42 -> 10185 | I42: 10185 | J42: DIRECT | L42: JAN | M42: =H42-I42 -> 0
A43: S19 | B43: LINAH WAITHIRA NDERU | C43: 0786286496 | D43: 10000 | E43: 10100 | H43: =D43+E43+G43+F43 -> 20100 | I43: =14000 -> 14000 | J43: UA91V3F4OI | L43: JAN | M43: =H43-I43 -> 6100 | N43: NEW TENANT 10TH
A44: S20 | B44: PHELISIA | C44: 0718117097 | E44: 10100 | F44: 450 | H44: =D44+E44+G44+F44 -> 10550 | I44: =5000+5000+2611 -> 12611 | J44: UA82T37XZ5 /UA72T35HD8 /UAU2T5AYOJ | K44: 7TH/8TH JAN | L44: JAN | M44: =H44-I44 -> -2061
A45: S21 | B45: MAINA | C45: 0797262139 | E45: 10100 | F45: 0 | H45: =D45+E45+G45+F45 -> 10100 | I45: =10270 -> 10270 | J45: UA71X36N5C | K45: 7TH JAN | L45: JAN | M45: =H45-I45 -> -170
A46: S22 | B46: JONA KIBET | C46: 0790405201 | E46: 10100 | F46: 450 | H46: =D46+E46+G46+F46 -> 10550 | I46: =10661 -> 10661 | J46: UA5QO2WROF | K46: 5TH JAN | L46: JAN | M46: =H46-I46 -> -111
A47: S23 | B47: CINDY | C47: 0726239783 | E47: 10100 | F47: 170 | H47: =D47+E47+G47+F47 -> 10270 | I47: =10270 -> 10270 | J47: UA5LX2U1DH | K47: 5TH JAN | L47: JAN | M47: =H47-I47 -> 0
A48: S24 | B48: YASHON | C48: 011167127 | E48: 10100 | F48: 170 | H48: =D48+E48+G48+F48 -> 10270 | I48: 10270 | J48: DIRECT | L48: JAN | M48: =H48-I48 -> 0
A49: S25 | B49: LIZZIE | C49: 0706359132 | E49: 10100 | F49: 300 | H49: =D49+E49+G49+F49 -> 10400 | I49: =10525 -> 10525 | J49: UA5U95S2NN | L49: JAN | M49: =H49-I49 -> -125
A50: S26 | B50: LUCY | C50: 0703357741 | E50: 10100 | F50: 60 | H50: =D50+E50+G50+F50 -> 10160 | I50: =10160 -> 10160 | J50: UAC853MOWG | L50: JAN | M50: =H50-I50 -> 0
A51: S27 | B51: DOROTHY | E51: 10100 | F51: 300 | H51: =D51+E51+G51+F51 -> 10400 | I51: =10440 -> 10440 | J51: UA2B12QDUE | K51: 2ND JAN | L51: JAN | M51: =H51-I51 -> -40
A52: S28 | B52: STELLA | C52: 0745586458 | E52: 10100 | F52: 0 | H52: =D52+E52+G52+F52 -> 10100 | I52: 10100 | J52: UA35G2VB9R | L52: JAN | M52: =H52-I52 -> 0
A53: S29 | B53: JUMA | E53: 10100 | F53: 150 | H53: =D53+E53+G53+F53 -> 10250 | I53: 10440 | J53: DIRECT | L53: JAN | M53: =H53-I53 -> -190
A54: S30 | B54: JOSEPH MUGO | C54: 0704339161 | E54: 9100 | F54: 150 | H54: =D54+E54+G54+F54 -> 9250 | I54: =9330 -> 9330 | J54: UA7SB5ZMGS | L54: JAN | M54: =H54-I54 -> -80
A55: S31 | B55: DUNCAN | C55: 0723879509 | E55: 9100 | F55: 150 | H55: =D55+E55+G55+F55 -> 9250 | I55: =9500 -> 9500 | J55: TLPC424XDA | L55: JAN | M55: =H55-I55 -> -250
A56: S32 | B56: VACANT | H56: =D56+E56+G56+F56 -> 0 | L56: JAN | M56: =H56-I56 -> 0
A57: Totals | D57: =SUM(D9:D55) -> 20000 | E57: =SUM(E9:E56) -> 422600 | F57: =SUM(F9:F56) -> 10860 | G57: =SUM(G9:G56) -> 16000 | H57: =SUM(H9:H56) -> 469460 | I57: =SUM(I9:I56) -> 441100 | M57: =SUM(M9:M56) -> 28360
A59: Deductions
A60: Less Management fees | I60: =6%*(I57-D57-F57) -> 24614.4
A61: TOTAL DEDUCTIONS | I61: =SUM(I60:I60) -> 24614.4
A63: BAL B/F | J63: Paid | L63: Paid | M63: Balance
A64: AMOUNT DUE | I64: =I61 -> 24614.4 | M64: =I64-J64-L64 -> 24614.4
A66: AUTHORISED BY JOSEPH GITHINJI | M66: 46053
E70: =I57/H57*100 -> 93.959017

Sheet FEBRUARY
C1: LOBBY ENTERPRISES
A2: PROPERTY MANAGERS AND ESTATE AGENTS
A3: FEB 2026
J4: P.O.BOX 11987
A5: STUDIO HAVEN | J5: TEL : 0722711933/4454322
A6: A/C | I6: Care taker | J6: ELIZABETH
I7: Phone no | J7: 0796292019
A8: HSE NO | B8: NAME | C8: PHONE NO | D8: DEPOSIT PAID | E8: MONTHLY RENT | F8: WATER BILL | G8: BAL B/D | H8: RENT DUE | I8: RENT PAID | J8: RCT NO | K8: DATE | L8: PERIOD | M8: BALANCE | N8: STATUS | O8: FORMS
A9: H1 | B9: ROSE | C9: 0707714065 | E9: 10100 | F9: 450 | G9: =JAN!M9 -> 0 | H9: =D9+E9+G9+F9 -> 10550 | I9: =10550 -> 10550 | J9: UB3HM5LYQQ | K9: 3RD FEB | L9: FEBRUARY | M9: =H9-I9 -> 0
A10: H2 | B10: BENSON | C10: 0741776284 | E10: 10100 | F10: 600 | G10: =JAN!M10 -> 0 | H10: =D10+E10+G10+F10 -> 10700 | I10: =10700 -> 10700 | J10: UB5AY5SDCV | K10: 5TH FEB | L10: FEBRUARY | M10: =H10-I10 -> 0 | O10: SIGNED
A11: H3 | B11: TESSA MARRIE | C11: 0716507709 | D11: 10000 | E11: 10100 | G11: =JAN!M11 -> 0 | H11: =D11+E11+G11+F11 -> 20100 | I11: =10000+10100 -> 20100 | J11: UB2OV5L09G /'UB3OV5PL45 | K11: 2ND/3RD FEB | L11: FEBRUARY | M11: =H11-I11 -> 0
A12: H4 | B12: CECILIA | C12: 0743724464/'0110082228 | E12: 10100 | F12: 450 | G12: =JAN!M12 -> -227 | H12: =D12+E12+G12+F12 -> 10323 | I12: 10627 | J12: UB60I5V021 | K12: 6TH FEB | L12: FEBRUARY | M12: =H12-I12 -> -304 | O12: SIGNED
A13: H5 | B13: PAUL | C13: 0723316248 | E13: 10100 | F13: 600 | G13: =JAN!M13 -> 0 | H13: =D13+E13+G13+F13 -> 10700 | I13: 10700 | J13: UB6OF60SH9 | K13: 6TH FEB | L13: FEBRUARY | M13: =H13-I13 -> 0 | O13: SIGNED
A14: H6 | B14: EUGENE | C14: 0792983014 | E14: 10100 | F14: 405 | G14: =JAN!M14 -> -55 | H14: =D14+E14+G14+F14 -> 10450 | I14: =10450 -> 10450 | J14: UB4EN5LDXD | K14: 4TH FEB | L14: FEBRUARY | M14: =H14-I14 -> 0 | O14: SIGNED
A15: H7 | B15: JAMES | C15: 0713161165 | E15: 10100 | F15: 450 | G15: =JAN!M15 -> -160 | H15: =D15+E15+G15+F15 -> 10390 | I15: =10550 -> 10550 | J15: UB56J5UMIL | K15: 5TH FEB | L15: FEBRUARY | M15: =H15-I15 -> -160
A16: H8 | B16: BONIFACE | C16: 0703962575 | E16: 12100 | F16: 750 | G16: =JAN!M16 -> 0 | H16: =D16+E16+G16+F16 -> 12850 | I16: =12850 -> 12850 | J16: UB32M5R783 | K16: 3RD FEB | L16: FEBRUARY | M16: =H16-I16 -> 0 | O16: SIGNED
A17: H9 | B17: ROBERT | C17: 0726405930 | E17: 14100 | F17: 450 | G17: =JAN!M17 -> 2000 | H17: =D17+E17+G17+F17 -> 16550 | I17: =16550 -> 16550 | L17: FEBRUARY | M17: =H17-I17 -> 0
A18: H10 | B18: BEATRICE | C18: 0711729058 | E18: 10100 | F18: 677 | G18: =JAN!M18 -> -77 | H18: =D18+E18+G18+F18 -> 10700 | I18: 10700 | J18: UB2RI5JKGB | K18: 2ND FEB | L18: FEBRUARY | M18: =H18-I18 -> 0 | O18: SIGNED
A19: H11 | B19: PETER | C19: 0708568404 | E19: 10100 | F19: 150 | G19: =JAN!M19 -> 9250 | H19: =D19+E19+G19+F19 -> 19500 | I19: =19500 -> 19500 | J19: UBAK86D19W | K19: 10TH FEB | L19: FEBRUARY | M19: =H19-I19 -> 0
A20: H12 | B20: GIDEON | C20: 0712026963 | E20: 10100 | F20: 300 | G20: =JAN!M20 -> 0 | H20: =D20+E20+G20+F20 -> 10400 | I20: =10400 -> 10400 | J20: UB4955NCJQ | K20: 4TH FEB | L20: FEBRUARY | M20: =H20-I20 -> 0 | O20: SIGNED
A21: H13 | B21: SHAWN RATEMO | C21: 0716484383/'0721832745 | E21: 10100 | F21: 300 | G21: =JAN!M21 -> 0 | H21: =D21+E21+G21+F21 -> 10400 | I21: =10000+400 -> 10400 | J21: UB67V60IG9 /UB77V63JK7 | K21: 6TH /7TH FEB | L21: FEBRUARY | M21: =H21-I21 -> 0 | O21: SIGNED
A22: H14 | B22: LAWRENCE | C22: 0713605808 | E22: 10100 | F22: 300 | G22: =JAN!M22 -> 16100 | H22: =D22+E22+G22+F22 -> 26500 | L22: FEBRUARY | M22: =H22-I22 -> 26500 | N22: LOCKED | O22: SIGNED
A23: H15 | B23: SIMON | C23: 0745935239 | D23: 10000 | E23: 10100 | F23: 150 | G23: =JAN!M23 -> -125 | H23: =D23+E23+G23+F23 -> 20125 | I23: =12000 -> 12000 | J23: UAU1F5D012 | K23: 30TH JAN | L23: FEBRUARY | M23: =H23-I23 -> 8125 | O23: SIGNED
A24: H16 | B24: KELVIN GITONGA | C24: 0792391382 | E24: 10100 | F24: 150 | G24: =JAN!M24 -> -105 | H24: =D24+E24+G24+F24 -> 10145 | I24: =10250 -> 10250 | J24: UB5R45KIZ7 | K24: 5TH FEB | L24: FEBRUARY | M24: =H24-I24 -> -105 | O24: SIGNED | P24: CR | Q24: =I57/H57*100 -> 95.883025
A25: S1 | B25: VIVIAN | C25: 0748596476 | E25: 10100 | F25: 450 | G25: =JAN!M25 -> -126 | H25: =D25+E25+G25+F25 -> 10424 | I25: 10550 | J25: UB6KD5V77I | K25: 6TH FEB | L25: FEBRUARY | M25: =H25-I25 -> -126 | O25: SIGNED
A26: S2 | B26: LINDA | C26: 0748689851 | E26: 10100 | F26: 150 | G26: =JAN!M26 -> 130 | H26: =D26+E26+G26+F26 -> 10380 | I26: =10380 -> 10380 | J26: UB45V5QPAV | K26: 4TH FEB | L26: FEBRUARY | M26: =H26-I26 -> 0 | O26: SIGNED
A27: S3 | B27: WARREN | C27: 0769883948 | E27: 10100 | F27: 450 | G27: =JAN!M27 -> -680 | H27: =D27+E27+G27+F27 -> 9870 | I27: =10550 -> 10550 | J27: UB39R5NYMO | K27: 3RD FEB | L27: FEBRUARY | M27: =H27-I27 -> -680 | O27: SIGNED
A28: S4 | B28: SCOLA | C28: 0793889379 | E28: 10100 | F28: 300 | G28: =JAN!M28 -> 0 | H28: =D28+E28+G28+F28 -> 10400 | I28: =10400 -> 10400 | J28: UB5SB77IA1 | K28: 5TH FEB | L28: FEBRUARY | M28: =H28-I28 -> 0 | P28: CR | Q28: 75.570748
A29: S5 | B29: CARETAKER | G29: =JAN!M29 -> 0 | H29: =D29+E29+G29+F29 -> 0 | L29: FEBRUARY
A30: S6 | B30: IMELDA | C30: 0723500330 | E30: 10100 | F30: 220 | G30: =JAN!M30 -> -20 | H30: =D30+E30+G30+F30 -> 10300 | I30: 10300 | J30: UB9D3647TO | K30: 9TH FEB | L30: FEBRUARY | M30: =H30-I30 -> 0 | N30: 10TH | O30: SIGNED | P30: 2 BROKEN PADLOCK ADD 1000
A31: S7 | B31: EVANS | C31: 0702377661 | E31: 10100 | F31: 30 | G31: =JAN!M31 -> -8 | H31: =D31+E31+G31+F31 -> 10122 | I31: 10130 | J31: UB3GH5SRXU | K31: 3RD FEB | L31: FEBRUARY | M31: =H31-I31 -> -8
A32: S8 | B32: BRIAN CHERUIYOT | C32: 0746324500 | E32: 10100 | F32: 300 | G32: =JAN!M32 -> 0 | H32: =D32+E32+G32+F32 -> 10400 | I32: 10400 | J32: UBB7Q6IVOX | K32: 11TH FEB | L32: FEBRUARY | M32: =H32-I32 -> 0 | N32: 11TH | O32: SIGNED
A33: S9 | B33: DORCAS | C33: 0723433108 | E33: 10100 | F33: 150 | G33: =JAN!M33 -> -170 | H33: =D33+E33+G33+F33 -> 10080 | I33: =10250 -> 10250 | J33: UB44763A1E | K33: 4TH FEB | L33: FEBRUARY | M33: =H33-I33 -> -170 | O33: SIGNED
A34: S10 | B34: MONICAH | C34: 0740454928 | E34: 10100 | F34: 150 | G34: =JAN!M34 -> -20 | H34: =D34+E34+G34+F34 -> 10230 | I34: =10250 -> 10250 | J34: UBBSG82QRZ | K34: 11TH FEB | L34: FEBRUARY | M34: =H34-I34 -> -20
A35: S11 | B35: IAN KAMAU | C35: 0745292688 | E35: 10100 | F35: 450 | G35: =JAN!M35 -> -170 | H35: =D35+E35+G35+F35 -> 10380 | I35: 10720 | J35: UBBMS6CJ15 | K35: 11TH FEB | L35: FEBRUARY | M35: =H35-I35 -> -340
A36: S12 | B36: JUSTINE | C36: 0724282631 | E36: 10100 | F36: 150 | G36: =JAN!M36 -> -170 | H36: =D36+E36+G36+F36 -> 10080 | I36: =10100 -> 10100 | L36: FEBRUARY | M36: =H36-I36 -> -20
A37: S13 | B37: DERRICK | C37: 0707280087 | E37: 10100 | F37: 300 | G37: =JAN!M37 -> -40 | H37: =D37+E37+G37+F37 -> 10360 | I37: =10400 -> 10400 | J37: UB6IA5XEBJ | K37: 6TH FEB | L37: FEBRUARY | M37: =H37-I37 -> -40
A38: S14 | B38: VINCENT | C38: 0798467289 | E38: 10100 | F38: 600 | G38: =JAN!M38 -> 0 | H38: =D38+E38+G38+F38 -> 10700 | I38: =10100+10600 -> 20700 | J38: UAP194RE18/UBQ197PK5L | K38: 25TH JAN | L38: FEBRUARY | M38: =H38-I38 -> -10000
A39: S15 | B39: ARON | C39: 0706195266 | E39: 10100 | F39: 340 | G39: =JAN!M39 -> -40 | H39: =D39+E39+G39+F39 -> 10400 | I39: 10400 | J39: UB15Q5Q20O | K39: 1ST FEB | L39: FEBRUARY | M39: =H39-I39 -> 0 | O39: SIGNED
A40: S16 | B40: BEN SAKWA | C40: 0789232363 | E40: 10100 | F40: 1200 | G40: =JAN!M40 -> 0 | H40: =D40+E40+G40+F40 -> 11300 | I40: =1200+10100 -> 11300 | J40: UB42A61CO0 | K40: 4TH FEB | L40: FEBRUARY | M40: =H40-I40 -> 0 | O40: SIGNED
A41: S17 | B41: SAID A SAID | D41: 10000 | E41: 10100 | F41: 0 | G41: =JAN!M41 -> 0 | H41: =D41+E41+G41+F41 -> 20100 | I41: =20100 -> 20100 | J41: UAV9A5BDPL | K41: 31ST JAN | L41: FEBRUARY | M41: =H41-I41 -> 0 | O41: SIGNED
A42: S18 | B42: LIZZIE NYAMBURA | C42: 0792838695 | E42: 10100 | F42: 200 | G42: =JAN!M42 -> 0 | H42: =D42+E42+G42+F42 -> 10300 | I42: =10300 -> 10300 | J42: UB56L5R7UV | K42: 5TH FEB | L42: FEBRUARY | M42: =H42-I42 -> 0 | O42: SIGNED
A43: S19 | B43: LINAH WAITHIRA NDERU | C43: 0786286496 | E43: 10100 | F43: 150 | G43: =JAN!M43 -> 6100 | H43: =D43+E43+G43+F43 -> 16350 | I43: =13500+150 -> 13650 | J43: UBA1V6E1J8 /UB41V5W5TN | K43: 4TH/10TH FEB | L43: FEBRUARY | M43: =H43-I43 -> 2700 | N43: REDUCING | O43: SIGNED
A44: S20 | B44: PHELISIA | C44: 0718117097 | E44: 10100 | F44: 750 | G44: =JAN!M44 -> -2061 | H44: =D44+E44+G44+F44 -> 8789 | I44: =10000 -> 10000 | J44: UB42T5PKMZ | K44: 4TH FEB | L44: FEBRUARY | M44: =H44-I44 -> -1211 | O44: SIGNED
A45: S21 | B45: JOEL MAINA | C45: 0797262139 | E45: 10100 | F45: 340 | G45: =JAN!M45 -> -170 | H45: =D45+E45+G45+F45 -> 10270 | I45: 10270 | J45: UB51X5XU7O | K45: 5TH FEB | L45: FEBRUARY | M45: =H45-I45 -> 0 | O45: SIGNED
A46: S22 | B46: JONA KIBET | C46: 0790405201 | E46: 10100 | F46: 750 | G46: =JAN!M46 -> -111 | H46: =D46+E46+G46+F46 -> 10739 | I46: =10850 -> 10850 | J46: UB4QO5LCAL | K46: 4TH FEB | L46: FEBRUARY | M46: =H46-I46 -> -111 | O46: SIGNED
A47: S23 | B47: CINDY | C47: 0726239783 | E47: 10100 | F47: 300 | G47: =JAN!M47 -> 0 | H47: =D47+E47+G47+F47 -> 10400 | I47: =10400 -> 10400 | J47: UB4LX5KYQO | K47: 4TH FEB | L47: FEBRUARY | M47: =H47-I47 -> 0
A48: S24 | B48: YASHON | C48: 0711167127 | E48: 10100 | F48: 170 | G48: =JAN!M48 -> 0 | H48: =D48+E48+G48+F48 -> 10270 | I48: 10270 | J48: UBBI96CY2J | K48: 11TH FEB | L48: FEBRUARY | M48: =H48-I48 -> 0 | O48: SIGNED
A49: S25 | B49: LIZZIE | C49: 0706359132 | E49: 10100 | F49: 300 | G49: =JAN!M49 -> -125 | H49: =D49+E49+G49+F49 -> 10275 | I49: 10400 | J49: UB5U971ISL | K49: 5TH FEB | L49: FEBRUARY | M49: =H49-I49 -> -125
A50: S26 | B50: LUCY | C50: 0703357741 | E50: 10100 | F50: 150 | G50: =JAN!M50 -> 0 | H50: =D50+E50+G50+F50 -> 10250 | I50: =10250 -> 10250 | J50: UB785601I6 | K50: 7TH FEB | L50: FEBRUARY | M50: =H50-I50 -> 0
A51: S27 | B51: DOROTHY | C51: 0793749115 | E51: 10100 | F51: 150 | G51: =JAN!M51 -> -40 | H51: =D51+E51+G51+F51 -> 10210 | I51: =10250 -> 10250 | J51: UB5B15YDUF | K51: 5TH FEB | L51: FEBRUARY | M51: =H51-I51 -> -40 | O51: SIGNED
A52: S28 | B52: STELLA | C52: 0745586458 | E52: 10100 | F52: 0 | G52: =JAN!M52 -> 0 | H52: =D52+E52+G52+F52 -> 10100 | I52: =10100 -> 10100 | J52: UBB5G6JQVC | K52: 11TH FEB | L52: FEBRUARY | M52: =H52-I52 -> 0
A53: S29 | B53: JUMA | E53: 10100 | F53: 300 | G53: =JAN!M53 -> -190 | H53: =D53+E53+G53+F53 -> 10210 | I53: =10440 -> 10440 | J53: UB1A25KQTX | K53: 1ST FEB | L53: FEBRUARY | M53: =H53-I53 -> -230
A54: S30 | B54: JOSEPH MUGO | C54: 0704339161 | E54: 10100 | F54: 300 | G54: =JAN!M54 -> -80 | H54: =D54+E54+G54+F54 -> 10320 | I54: =10400 -> 10400 | J54: UB5SB77IA1 | K54: 5TH FEB | L54: FEBRUARY | M54: =H54-I54 -> -80 | O54: SIGNED
A55: S31 | B55: DUNCAN | C55: 0723879509 | E55: 10100 | F55: 300 | G55: =JAN!M55 -> -250 | H55: =D55+E55+G55+F55 -> 10150 | I55: =10400 -> 10400 | J55: UB1C45KWB5 | L55: FEBRUARY | M55: =H55-I55 -> -250 | O55: SIGNED
A56: S32 | B56: EZEKIEL KAIKAI | C56: 0794799285 | D56: 9500 | E56: 9600 | F56: 0 | G56: =JAN!M56 -> 0 | H56: =D56+E56+G56+F56 -> 19100 | I56: =19200 -> 19200 | J56: UBA1V6E1J8 | K56: 9TH FEB | L56: FEBRUARY | M56: =H56-I56 -> -100 | O56: SIGNED
A57: Totals | E57: =SUM(E9:E56) -> 480200 | F57: =SUM(F9:F56) -> 15582 | G57: =SUM(G9:G56) -> 28360 | H57: =SUM(H9:H56) -> 563642 | I57: =SUM(I9:I56) -> 540437 | M57: =SUM(M9:M56) -> 23205
A59: Deductions
A60: Less Management fees | I60: =6%*I57 -> 32426.22
A61: TOTAL DEDUCTIONS | I61: =SUM(I60:I60) -> 32426.22
A63: BAL B/F | J63: Paid | L63: Paid | M63: Balance
A64: AMOUNT DUE | I64: =I61 -> 32426.22 | M64: =I64-J64-L64 -> 32426.22
A66: AUTHORISED BY JOSEPH GITHINJI | M66: 46053
E70: =I57/H57*100 -> 95.883025

Sheet MARCH
C1: LOBBY ENTERPRISES
A2: PROPERTY MANAGERS AND ESTATE AGENTS
A3: MARCH 2026
J4: P.O.BOX 11987
A5: STUDIO HAVEN | J5: TEL : 0722711933/4454322
A6: A/C | I6: Care taker | J6: ELIZABETH
I7: Phone no | J7: 0796292019
A8: HSE NO | B8: NAME | C8: PHONE NO | D8: DEPOSIT PAID | E8: MONTHLY RENT | F8: WATER BILL | G8: BAL B/D | H8: RENT DUE | I8: RENT PAID | J8: RCT NO | K8: DATE | L8: PERIOD | M8: BALANCE | N8: STATUS | O8: FORMS
A9: H1 | B9: ROSE | C9: 0707714065 | E9: 10100 | F9: 600 | G9: =FEBRUARY!M9 -> 0 | H9: =D9+E9+G9+F9 -> 10700 | I9: =10700 -> 10700 | J9: UC5HM8ETCZ | K9: 5TH MARCH | L9: MARCH | M9: =H9-I9 -> 0
A10: H2 | B10: BENSON | C10: 0741776284 | E10: 10100 | F10: 630 | G10: =FEBRUARY!M10 -> 0 | H10: =D10+E10+G10+F10 -> 10730 | I10: =10730 -> 10730 | J10: UC7AY8KXQJ | K10: 7TH MARCH | L10: MARCH | M10: =H10-I10 -> 0 | O10: SIGNED
A11: H3 | B11: TESSA MARRIE | C11: 0716507709 | E11: 10100 | F11: 420 | G11: =FEBRUARY!M11 -> 0 | H11: =D11+E11+G11+F11 -> 10520 | I11: =41000 -> 41000 | J11: UC4OV8H0W7 | K11: 4TH MARCH | L11: MARCH | M11: =H11-I11 -> -30480
A12: H4 | B12: CECILIA | C12: 0743724464/'0110082228 | E12: 10100 | F12: 360 | G12: =FEBRUARY!M12 -> -304 | H12: =D12+E12+G12+F12 -> 10156 | I12: =5000+5460 -> 10460 | J12: UCC0I8YJ7H /UCE0I96L4Z | K12: 12TH/14TH MARCH | L12: MARCH | M12: =H12-I12 -> -304 | N12: 14TH | O12: SIGNED
A13: H5 | B13: PAUL | C13: 0723316248 | E13: 10100 | F13: 585 | G13: =FEBRUARY!M13 -> 0 | H13: =D13+E13+G13+F13 -> 10685 | I13: =10600 -> 10600 | J13: UC8OF8SCHV | K13: 8TH MARCH | L13: MARCH | M13: =H13-I13 -> 85 | O13: SIGNED
A14: H6 | B14: EUGENE | C14: 0792983014 | E14: 10100 | F14: 165 | G14: =FEBRUARY!M14 -> 0 | H14: =D14+E14+G14+F14 -> 10265 | I14: =10165 -> 10165 | J14: UC5EN8ASG3 | K14: 5TH MARCH | L14: MARCH | M14: =H14-I14 -> 100 | O14: SIGNED
A15: H7 | B15: JAMES | C15: 0713161165 | E15: 10100 | F15: 150 | G15: =FEBRUARY!M15 -> -160 | H15: =D15+E15+G15+F15 -> 10090 | I15: =10250 -> 10250 | J15: UC56J8HQDS | K15: 5TH MARCH | L15: MARCH | M15: =H15-I15 -> -160
A16: H8 | B16: BONIFACE | C16: 0703962575 | E16: 12100 | F16: 720 | G16: =FEBRUARY!M16 -> 0 | H16: =D16+E16+G16+F16 -> 12820 | I16: =12820 -> 12820 | J16: UC52M8KO7O | K16: 5TH MARCH | L16: MARCH | M16: =H16-I16 -> 0 | O16: SIGNED
A17: H9 | B17: ROBERT | C17: 0726405930 | E17: 14100 | F17: 525 | G17: =FEBRUARY!M17 -> 0 | H17: =D17+E17+G17+F17 -> 14625 | L17: MARCH | M17: =H17-I17 -> 14625 | N17: HOSPITALIZED
A18: H10 | B18: BEATRICE | C18: 0711729058 | E18: 10100 | F18: 765 | G18: =FEBRUARY!M18 -> 0 | H18: =D18+E18+G18+F18 -> 10865 | I18: =10765 -> 10765 | J18: UC7RI8M5EP | K18: 7TH MARCH | L18: MARCH | M18: =H18-I18 -> 100 | O18: SIGNED
A19: H11 | B19: PETER | C19: 0708568404 | E19: 10100 | F19: 165 | G19: =FEBRUARY!M19 -> 0 | H19: =D19+E19+G19+F19 -> 10265 | I19: 10265 | J19: UC3K88C9U2 | K19: 3RD MARCH | L19: MARCH | M19: =H19-I19 -> 0
A20: H12 | B20: GIDEON | C20: 0712026963 | E20: 10100 | F20: 105 | G20: =FEBRUARY!M20 -> 0 | H20: =D20+E20+G20+F20 -> 10205 | I20: =10205 -> 10205 | J20: UC5958E3YK | K20: 5TH MARCH | L20: MARCH | M20: =H20-I20 -> 0 | O20: SIGNED
A21: H13 | B21: SHAWN RATEMO | C21: 0716484383/'0721832745 | E21: 10100 | F21: 135 | G21: =FEBRUARY!M21 -> 0 | H21: =D21+E21+G21+F21 -> 10235 | I21: =10300 -> 10300 | J21: UC77V8R06V | K21: 7TH MARCH | L21: MARCH | M21: =H21-I21 -> -65 | O21: SIGNED
A22: H14 | B22: SAID A SAID | C22: 0719488891 | E22: 10100 | F22: 615 | G22: 0 | H22: =D22+E22+G22+F22 -> 10715 | I22: =10715 -> 10715 | J22: UC15K86V63 /UC75K8QF01 | K22: 1ST/7TH MARCH | L22: MARCH | M22: =H22-I22 -> 0 | O22: SIGNED
A23: H15 | B23: SIMON | C23: 0745935239 | E23: 10100 | F23: 915 | G23: =FEBRUARY!M23 -> 8125 | H23: =D23+E23+G23+F23 -> 19140 | I23: =14915 -> 14915 | J23: UC41F8I15J | K23: 4TH MARCH | L23: MARCH | M23: =H23-I23 -> 4225 | N23: REDUCING | O23: SIGNED
A24: H16 | B24: KELVIN GITONGA | C24: 0792391382 | E24: 10100 | F24: 135 | G24: =FEBRUARY!M24 -> -105 | H24: =D24+E24+G24+F24 -> 10130 | I24: =10235 -> 10235 | J24: UC5R485R0C | K24: 5TH MARCH | L24: MARCH | M24: =H24-I24 -> -105 | O24: SIGNED | P24: CR | Q24: =I57/H57*100 -> 109.95195
A25: S1 | B25: VIVIAN | C25: 0748596476 | E25: 10100 | F25: 525 | G25: =FEBRUARY!M25 -> -126 | H25: =D25+E25+G25+F25 -> 10499 | I25: =10525 -> 10525 | J25: UC7KD8LF1L | K25: 7TH MARCH | L25: MARCH | M25: =H25-I25 -> -26 | O25: SIGNED
A26: S2 | B26: LINDA | C26: 0748689851 | E26: 10100 | F26: 165 | G26: =FEBRUARY!M26 -> 0 | H26: =D26+E26+G26+F26 -> 10265 | I26: =10265 -> 10265 | J26: UC55V8H5QK | K26: 5TH MARCH | L26: MARCH | M26: =H26-I26 -> 0 | O26: SIGNED
A27: S3 | B27: WARREN | C27: 0769883948 | E27: 10100 | F27: 420 | G27: =FEBRUARY!M27 -> -680 | H27: =D27+E27+G27+F27 -> 9840 | I27: =10520 -> 10520 | J27: UC39R8C6T3 | K27: 3RD MARCH | L27: MARCH | M27: =H27-I27 -> -680 | O27: SIGNED
A28: S4 | B28: SCOLA | C28: 0793889379 | E28: 10100 | F28: 150 | G28: =FEBRUARY!M28 -> 0 | H28: =D28+E28+G28+F28 -> 10250 | I28: =8900+1100+250 -> 10250 | J28: UC3HE8ALL5 /UC3HE8AJSA /UCBHE90FP8 | K28: 3RD/11TH MARCH | L28: MARCH | M28: =H28-I28 -> 0 | P28: CR | Q28: 75.570748
A29: S5 | B29: CARETAKER | G29: =FEBRUARY!M29 -> 0 | H29: =D29+E29+G29+F29 -> 0 | L29: MARCH | M29: =H29-I29 -> 0
A30: S6 | B30: IMELDA | C30: 0723500330 | E30: 10100 | F30: 135 | G30: =FEBRUARY!M30 -> 0 | H30: =D30+E30+G30+F30 -> 10235 | I30: =6500+3735 -> 10235 | J30: UCBD38Z2FB | K30: 11TH/18TH MARCH | L30: MARCH | M30: =H30-I30 -> 0 | N30: 10TH | O30: SIGNED | P30: 2 BROKEN PADLOCK ADD 1000
A31: S7 | B31: EVANS | C31: 0702377661 | E31: 10100 | F31: 15 | G31: =FEBRUARY!M31 -> -8 | H31: =D31+E31+G31+F31 -> 10107 | I31: =10115 -> 10115 | J31: UC5GH8NQ0E | K31: 5TH MARCH | L31: MARCH | M31: =H31-I31 -> -8
A32: S8 | B32: BRIAN CHERUIYOT | C32: 0746324500 | E32: 10100 | F32: 1245 | G32: =FEBRUARY!M32 -> 0 | H32: =D32+E32+G32+F32 -> 11345 | I32: =10000+1345 -> 11345 | J32: UCB7Q95V5X/UCE7Q9G9CD | K32: 11TH MARCH | L32: MARCH | M32: =H32-I32 -> 0 | N32: 11TH | O32: SIGNED
A33: S9 | B33: DORCAS | C33: 0723433108 | E33: 10100 | F33: 105 | G33: =FEBRUARY!M33 -> -170 | H33: =D33+E33+G33+F33 -> 10035 | I33: =10205 -> 10205 | J33: UC5478SORT | K33: 5TH MARCH | L33: MARCH | M33: =H33-I33 -> -170 | O33: SIGNED
A34: S10 | B34: MONICAH | C34: 0740454928 | E34: 10100 | F34: 195 | G34: =FEBRUARY!M34 -> -20 | H34: =D34+E34+G34+F34 -> 10275 | I34: =10195 -> 10195 | J34: UCASG9DEZI | K34: 10TH MARCH | L34: MARCH | M34: =H34-I34 -> 80
A35: S11 | B35: IAN KAMAU | C35: 0745292688 | E35: 10100 | F35: 210 | G35: =FEBRUARY!M35 -> -340 | H35: =D35+E35+G35+F35 -> 9970 | I35: =20400 -> 20400 | J35: UCCMS92YRZ | K35: 12TH MARCH | L35: MARCH | M35: =H35-I35 -> -10430 | N35: 14TH
A36: S12 | B36: JUSTINE | C36: 0724282631 | E36: 10100 | F36: 45 | G36: =FEBRUARY!M36 -> -20 | H36: =D36+E36+G36+F36 -> 10125 | I36: =10145 -> 10145 | J36: R3JK6CLTK82 | K36: 8TH MARCH | L36: MARCH | M36: =H36-I36 -> -20
A37: S13 | B37: DERRICK | C37: 0707280087 | E37: 10100 | F37: 270 | G37: =FEBRUARY!M37 -> -40 | H37: =D37+E37+G37+F37 -> 10330 | I37: =10370 -> 10370 | J37: UC8IA8R23L | K37: 8TH MARCH | L37: MARCH | M37: =H37-I37 -> -40
A38: S14 | B38: VINCENT | C38: 0798467289 | E38: 10100 | F38: 510 | G38: =FEBRUARY!M38 -> -10000 | H38: =D38+E38+G38+F38 -> 610 | I38: =610+10100 -> 10710 | J38: UC8198MW7G /UCQ19AIA45 | K38: 8TH/26TH MARCH | L38: MARCH | M38: =H38-I38 -> -10100
A39: S15 | B39: ARON | C39: 0706195266 | E39: 10100 | F39: 210 | G39: =FEBRUARY!M39 -> 0 | H39: =D39+E39+G39+F39 -> 10310 | I39: =10210 -> 10210 | J39: UC85Q90VVK | K39: 8TH MARCH | L39: MARCH | M39: =H39-I39 -> 100 | O39: SIGNED
A40: S16 | B40: BEN SAKWA | C40: 0789232363 | E40: 10100 | F40: 825 | G40: =FEBRUARY!M40 -> 0 | H40: =D40+E40+G40+F40 -> 10925 | I40: =10100+825 -> 10925 | J40: UBO2A7XZ5J | K40: 24TH FEB | L40: MARCH | M40: =H40-I40 -> 0 | O40: SIGNED
A41: S17 | B41: VACANT | G41: =FEBRUARY!M41 -> 0 | H41: =D41+E41+G41+F41 -> 0 | M41: =H41-I41 -> 0 | O41: SIGNED
A42: S18 | B42: LIZZIE NYAMBURA | C42: 0792838695 | E42: 10100 | F42: 300 | G42: =FEBRUARY!M42 -> 0 | H42: =D42+E42+G42+F42 -> 10400 | I42: =10702 -> 10702 | J42: UC56L8DBPJ | K42: 5TH MARCH | L42: MARCH | M42: =H42-I42 -> -302 | O42: SIGNED
A43: S19 | B43: LINAH WAITHIRA NDERU | C43: 0786286496 | E43: 10100 | F43: 135 | G43: =FEBRUARY!M43 -> 2700 | H43: =D43+E43+G43+F43 -> 12935 | I43: =135+12000 -> 12135 | J43: UC41V8IX1U/UC91V8XJ0K | K43: 4TH/9TH MARCH | L43: MARCH | M43: =H43-I43 -> 800 | N43: REDUCING | O43: SIGNED
A44: S20 | B44: PHELISIA | C44: 0718117097 | E44: 10100 | F44: 525 | G44: =FEBRUARY!M44 -> -1211 | H44: =D44+E44+G44+F44 -> 9414 | I44: =10205+4000 -> 14205 | J44: UC4B18GXDC /UCQ2TAJO3S | K44: 4TH/26TH MARCH | L44: MARCH | M44: =H44-I44 -> -4791 | O44: SIGNED
A45: S21 | B45: JOEL MAINA | C45: 0797262139 | E45: 10100 | F45: 390 | G45: =FEBRUARY!M45 -> 0 | H45: =D45+E45+G45+F45 -> 10490 | I45: =10390 -> 10390 | J45: UC91X8WT2D | K45: 9TH MARCH | L45: MARCH | M45: =H45-I45 -> 100 | O45: SIGNED
A46: S22 | B46: JONA KIBET | C46: 0790405201 | E46: 10100 | F46: 705 | G46: =FEBRUARY!M46 -> -111 | H46: =D46+E46+G46+F46 -> 10694 | I46: =10805 -> 10805 | J46: UC5QO8D284 | K46: 5TH MARCH | L46: MARCH | M46: =H46-I46 -> -111 | O46: SIGNED
A47: S23 | B47: CINDY | C47: 0726239783 | E47: 10100 | F47: 0 | G47: =FEBRUARY!M47 -> 0 | H47: =D47+E47+G47+F47 -> 10100 | I47: =10100 -> 10100 | J47: UC5LX8AGJ0 | K47: 5TH MARCH | L47: MARCH | M47: =H47-I47 -> 0
A48: S24 | B48: YASHON | C48: 0711167127 | E48: 10100 | F48: 90 | G48: =FEBRUARY!M48 -> 0 | H48: =D48+E48+G48+F48 -> 10190 | I48: =10190 -> 10190 | J48: UC9I98RYCB | K48: 9TH MARCH | L48: MARCH | M48: =H48-I48 -> 0 | O48: SIGNED
A49: S25 | B49: LIZZIE | C49: 0706359132 | E49: 10100 | F49: 435 | G49: =FEBRUARY!M49 -> -125 | H49: =D49+E49+G49+F49 -> 10410 | I49: =10535 -> 10535 | J49: UC5U9882BI | K49: 5TH MARCH | L49: MARCH | M49: =H49-I49 -> -125
A50: S26 | B50: LUCY | C50: 0703357741 | E50: 10100 | F50: 300 | G50: =FEBRUARY!M50 -> 0 | H50: =D50+E50+G50+F50 -> 10400 | I50: =10400 -> 10400 | J50: UC6858K5TG | K50: 6TH MARCH | L50: MARCH | M50: =H50-I50 -> 0
A51: S27 | B51: DOROTHY | C51: 0793749115 | E51: 10100 | F51: 105 | G51: =FEBRUARY!M51 -> -40 | H51: =D51+E51+G51+F51 -> 10165 | I51: =10205 -> 10205 | J51: UC4B18GXDC | K51: 4TH MARCH | L51: MARCH | M51: =H51-I51 -> -40 | O51: SIGNED
A52: S28 | B52: STELLA | C52: 0745586458 | E52: 10100 | F52: 0 | G52: =FEBRUARY!M52 -> 0 | H52: =D52+E52+G52+F52 -> 10100 | I52: =10000 -> 10000 | J52: UCA5G96557 | K52: 10TH MARCH | L52: MARCH | M52: =H52-I52 -> 100
A53: S29 | B53: JUMA | C53: 0702146655 | E53: 10100 | F53: 285 | G53: =FEBRUARY!M53 -> -230 | H53: =D53+E53+G53+F53 -> 10155 | I53: =10385 -> 10385 | J53: UC4A28H8ID | K53: 4TH MARCH | L53: MARCH | M53: =H53-I53 -> -230
A54: S30 | B54: JOSEPH MUGO | C54: 0704339161 | E54: 10100 | F54: 285 | G54: =FEBRUARY!M54 -> -80 | H54: =D54+E54+G54+F54 -> 10305 | I54: =10385 -> 10385 | J54: UC5SB8FV86 | K54: 5TH MARCH | L54: MARCH | M54: =H54-I54 -> -80 | O54: SIGNED
A55: S31 | B55: DUNCAN | C55: 0723879509 | E55: 10100 | F55: 150 | G55: =FEBRUARY!M55 -> -250 | H55: =D55+E55+G55+F55 -> 10000 | I55: =10000 -> 10000 | J55: UC1C488NGA | K55: 1ST MARCH | L55: MARCH | M55: =H55-I55 -> 0 | O55: SIGNED
A56: S32 | B56: EZEKIEL KAIKAI | C56: 0794799285 | E56: 9600 | F56: 315 | G56: =FEBRUARY!M56 -> -100 | H56: =D56+E56+G56+F56 -> 9815 | I56: =9600+315+10000 -> 19915 | J56: UC29V7XN7Q/UC39V82OSI /UCR9VAEQGQ | K56: 2ND/3RD /27TH MARCH | L56: MARCH | M56: =H56-I56 -> -10100 | O56: SIGNED
A57: Totals | E57: =SUM(E9:E56) -> 470100 | F57: =SUM(,F9:F56) -> 16035 | G57: =SUM(G9:G56) -> -3295 | H57: =SUM(H9:H56) -> 482840 | I57: =SUM(I9:I56) -> 530892 | M57: =SUM(M9:M56) -> -48052
A59: Deductions
A60: Less Management fees | I60: =6%*I57 -> 31853.52
A61: PIPE RANGE | I61: =1000 -> 1000
A62: TOTAL DEDUCTIONS | I62: =SUM(I60:I61) -> 32853.52
A64: BAL B/F | J64: Paid | L64: Paid | M64: Balance
A65: AMOUNT DUE | I65: =I62 -> 32853.52 | M65: =I65-J65-L65 -> 32853.52
A67: AUTHORISED BY JOSEPH GITHINJI | M67: 46053
E71: =I57/H57*100 -> 109.95195

Sheet APR
C1: LOBBY ENTERPRISES
A2: PROPERTY MANAGERS AND ESTATE AGENTS
A3: APR 2026
J4: P.O.BOX 11987
A5: STUDIO HAVEN | J5: TEL : 0722711933/4454322
A6: A/C | I6: Care taker | J6: ELIZABETH
I7: Phone no | J7: 0796292019
A8: HSE NO | B8: NAME | C8: PHONE NO | D8: DEPOSIT PAID | E8: MONTHLY RENT | F8: WATER BILL | G8: BAL B/D | H8: RENT DUE | I8: RENT PAID | J8: RCT NO | K8: DATE | L8: PERIOD | M8: BALANCE | N8: STATUS | O8: FORMS
A9: H1 | B9: ROSE | C9: 0707714065 | E9: 10100 | F9: 465 | G9: =MARCH!M9 -> 0 | H9: =D9+E9+G9+F9 -> 10565 | I9: 10565 | J9: UD4HMBJUQT | K9: 46116 | L9: APR | M9: =H9-I9 -> 0
A10: H2 | B10: BENSON | C10: 0741776284 | E10: 10100 | F10: 855 | G10: =MARCH!M10 -> 0 | H10: =D10+E10+G10+F10 -> 10955 | I10: 10950 | J10: UD8AY00TG6 | K10: 8/4/2026 | L10: APR | M10: =H10-I10 -> 5 | O10: SIGNED
A11: H3 | B11: TESSA MARRIE | C11: 0716507709 | E11: 10100 | F11: 585 | G11: =MARCH!M11 -> -30480 | H11: =D11+E11+G11+F11 -> -19795 | L11: APR | M11: =H11-I11 -> -19795
A12: H4 | B12: CECILIA | C12: 0743724464/'0110082228 | E12: 10100 | F12: 510 | G12: =MARCH!M12 -> -304 | H12: =D12+E12+G12+F12 -> 10306 | I12: 10000 | J12: UE20I2Q7XR/.UEB013SDFA | K12: 2ND MAY/11TH MAY | L12: APR | M12: =H12-I12 -> 306 | N12: PAID 5000 2ND MAY | O12: SIGNED
A13: H5 | B13: PAUL | C13: 0723316248 | E13: 10100 | F13: 810 | G13: =MARCH!M13 -> 85 | H13: =D13+E13+G13+F13 -> 10995 | I13: 10000 | J13: UD6OF00TLM | K13: 6TH APRIL | L13: APR | M13: =H13-I13 -> 995 | O13: SIGNED
A14: H6 | B14: EUGENE | C14: 0792983014 | H14: =D14+E14+G14+F14 -> 0 | L14: APR | M14: =H14-I14 -> 0 | N14: EVICTED/MICROWAVE RETAINED TO RECOVER REPAIR COSTS | O14: SIGNED
A15: H7 | B15: JAMES | C15: 0713161165 | E15: 10100 | F15: 570 | G15: =MARCH!M15 -> -160 | H15: =D15+E15+G15+F15 -> 10510 | I15: 10250 | J15: UD36JBFL17 | K15: 46085 | L15: APR | M15: =H15-I15 -> 260
A16: H8 | B16: BONIFACE | C16: 0703962575 | E16: 12100 | F16: 810 | G16: =MARCH!M16 -> 0 | H16: =D16+E16+G16+F16 -> 12910 | I16: 12910 | J16: UD72MO69KI | K16: 7/4/2026 | L16: APR | M16: =H16-I16 -> 0 | O16: SIGNED
A17: H9 | B17: ROBERT | C17: 0726405930 | E17: 14100 | F17: 300 | G17: =MARCH!M17 -> 14625 | H17: =D17+E17+G17+F17 -> 29025 | I17: =20000+15000 -> 35000 | J17: UD413BK2H/UDU132H744 | K17: 46116 | L17: APR | M17: =H17-I17 -> -5975
A18: H10 | B18: BEATRICE | C18: 0711729058 | E18: 10100 | F18: 630 | G18: =MARCH!M18 -> 100 | H18: =D18+E18+G18+F18 -> 10830 | I18: 10630 | J18: UD8RIO2OID | K18: 8/4/2026 | L18: APR | M18: =H18-I18 -> 200 | O18: SIGNED
A19: H11 | B19: PETER | C19: 0708568404 | E19: 10100 | F19: 180 | G19: =MARCH!M19 -> 0 | H19: =D19+E19+G19+F19 -> 10280 | I19: 10280 | J19: UD4K8BLKNL | K19: 46116 | L19: APR | M19: =H19-I19 -> 0
A20: H12 | B20: GIDEON | C20: 0712026963 | E20: 10100 | F20: 180 | G20: =MARCH!M20 -> 0 | H20: =D20+E20+G20+F20 -> 10280 | I20: 10280 | J20: UD695BR3DJ | K20: 46177 | L20: APR | M20: =H20-I20 -> 0 | O20: SIGNED
A21: H13 | B21: SHAWN RATEMO | C21: 0721832745 | E21: 10100 | F21: 540 | G21: =MARCH!M21 -> -65 | H21: =D21+E21+G21+F21 -> 10575 | I21: 10300 | J21: UD67V05HYO | K21: 6TH APRIL | L21: APR | M21: =H21-I21 -> 275 | O21: SIGNED
A22: H14 | B22: SAID A SAID | C22: 0719488891 | E22: 10100 | F22: -30 | G22: =MARCH!M22 -> 0 | H22: =D22+E22+G22+F22 -> 10070 | I22: 10445 | J22: UD3S89ZW03 | K22: 46085 | L22: APR | M22: =H22-I22 -> -375 | O22: SIGNED
A23: H15 | B23: SIMON | C23: 0745935239 | E23: 10100 | F23: 1215 | G23: =MARCH!M23 -> 4225 | H23: =D23+E23+G23+F23 -> 15540 | I23: 11330 | J23: UD8IF08HQ | K23: 8TH APRIL | L23: APR | M23: =H23-I23 -> 4210 | O23: SIGNED
A24: H16 | B24: KELVIN GITONGA | C24: 0792391382 | E24: 10100 | F24: 255 | G24: =MARCH!M24 -> -105 | H24: =D24+E24+G24+F24 -> 10250 | I24: 10355 | J24: UD5R4BDPTH | K24: 46146 | L24: APR | M24: =H24-I24 -> -105 | O24: SIGNED | P24: CR | Q24: =I57/H57*100 -> 111.05098
A25: S1 | B25: VIVIAN | C25: 0748596476 | E25: 10100 | F25: 765 | G25: =MARCH!M25 -> -26 | H25: =D25+E25+G25+F25 -> 10839 | I25: 10765 | J25: UD3KDBIPCD | K25: 46085 | L25: APR | M25: =H25-I25 -> 74 | O25: SIGNED
A26: S2 | B26: LINDA | C26: 0748689851 | E26: 10100 | F26: 225 | G26: =MARCH!M26 -> 0 | H26: =D26+E26+G26+F26 -> 10325 | I26: 10325 | J26: UD45VBOJ30 | K26: 46116 | L26: APR | M26: =H26-I26 -> 0 | O26: SIGNED
A27: S3 | B27: WARREN | C27: 0769883948 | E27: 10100 | F27: 495 | G27: =MARCH!M27 -> -680 | H27: =D27+E27+G27+F27 -> 9915 | I27: 10595 | J27: UD39RBK81D | K27: 46085 | L27: APR | M27: =H27-I27 -> -680 | O27: SIGNED
A28: S4 | B28: SCOLA | C28: 0793889379 | E28: 10100 | F28: 225 | G28: =MARCH!M28 -> 0 | H28: =D28+E28+G28+F28 -> 10325 | I28: 10250 | J28: UD4HEBMPCV | K28: 4TH APRIL | L28: APR | M28: =H28-I28 -> 75 | P28: CR | Q28: 75.570748
A29: S5 | B29: CARETAKER | F29: 0 | G29: =MARCH!M29 -> 0 | H29: =D29+E29+G29+F29 -> 0 | L29: APR | M29: =H29-I29 -> 0
A30: S6 | B30: IMELDA | C30: 0723500330 | E30: 10100 | F30: 270 | G30: =MARCH!M30 -> 0 | H30: =D30+E30+G30+F30 -> 10370 | I30: 10300 | J30: UD4D3BI7PH | K30: 46116 | L30: APR | M30: =H30-I30 -> 70 | O30: SIGNED | P30: 2 BROKEN PADLOCK ADD 1000
A31: S7 | B31: EVANS | C31: 0702377661 | E31: 10100 | F31: 30 | G31: =MARCH!M31 -> -8 | H31: =D31+E31+G31+F31 -> 10122 | I31: 10130 | J31: UD4J4BHPK4 | K31: 4/4/2026 | L31: APR | M31: =H31-I31 -> -8
A32: S8 | B32: BRIAN CHERUIYOT | C32: 0746324500 | E32: 10100 | F32: 840 | G32: =MARCH!M32 -> 0 | H32: =D32+E32+G32+F32 -> 10940 | I32: 10900 | J32: UDS7Q2O20S | K32: 28/4/26 | L32: APR | M32: =H32-I32 -> 40 | O32: SIGNED
A33: S9 | B33: DORCAS | C33: 0723433108 | E33: 10100 | F33: 240 | G33: =MARCH!M33 -> -170 | H33: =D33+E33+G33+F33 -> 10170 | I33: 10340 | J33: UD44703C9J | K33: 46116 | L33: APR | M33: =H33-I33 -> -170 | O33: SIGNED
A34: S10 | B34: MONICAH | C34: 0740454928 | E34: 10100 | F34: 240 | G34: =MARCH!M34 -> 80 | H34: =D34+E34+G34+F34 -> 10420 | I34: 10320 | J34: UD4LRBC8MI | K34: 4TH APRIL | L34: APR | M34: =H34-I34 -> 100
A35: S11 | B35: IAN KAMAU | C35: 0745292688 | E35: 10100 | F35: 210 | G35: =MARCH!M35 -> -10430 | H35: =D35+E35+G35+F35 -> -120 | I35: 10310 | J35: UDFMSOWAX5 | K35: 15/4/26 | L35: APR | M35: =H35-I35 -> -10430
A36: S12 | B36: JUSTINE | C36: 0724282631 | E36: 10100 | F36: 165 | G36: =MARCH!M36 -> -20 | H36: =D36+E36+G36+F36 -> 10245 | I36: =10150+10300 -> 20450 | J36: I3KSGDVSMKN/Y3LUKJZ5XFV | K36: 4/4/2026/1/5/2026 | L36: APR | M36: =H36-I36 -> -10205
A37: S13 | B37: DERRICK | C37: 0707280087 | E37: 10100 | F37: 285 | G37: =MARCH!M37 -> -40 | H37: =D37+E37+G37+F37 -> 10345 | I37: 10370 | J37: UD6IABTCV9 | K37: 6TH APRIL | L37: APR | M37: =H37-I37 -> -25
A38: S14 | B38: VINCENT | C38: 0798467289 | E38: 10100 | F38: 315 | G38: =MARCH!M38 -> -10100 | H38: =D38+E38+G38+F38 -> 315 | L38: APR | M38: =H38-I38 -> 315
A39: S15 | B39: ARON | C39: 0706195266 | E39: 10100 | F39: 150 | G39: =MARCH!M39 -> 100 | H39: =D39+E39+G39+F39 -> 10350 | I39: 10150 | J39: UD45Q01NRO | K39: 46116 | L39: APR | M39: =H39-I39 -> 200 | O39: SIGNED
A40: S16 | B40: BEN SAKWA | E40: 10100 | F40: 1575 | G40: =MARCH!M40 -> 0 | H40: =D40+E40+G40+F40 -> 11675 | I40: =10100+1575 -> 11675 | J40: UCR2AB2BE6 | K40: 27TH MARCH | L40: APR | M40: =H40-I40 -> 0 | O40: SIGNED
A41: S17 | B41: VACANT | G41: =MARCH!M41 -> 0 | H41: =D41+E41+G41+F41 -> 0 | L41: APR | M41: =H41-I41 -> 0 | O41: SIGNED
A42: S18 | B42: LIZZIE NYAMBURA | C42: 0792838695 | E42: 10100 | F42: 150 | G42: =MARCH!M42 -> -302 | H42: =D42+E42+G42+F42 -> 9948 | I42: 10000 | J42: UD16LB62Q0 | K42: 46026 | L42: APR | M42: =H42-I42 -> -52 | O42: SIGNED
A43: S19 | B43: LINAH WAITHIRA NDERU | C43: 0786286496 | E43: 10100 | F43: 15 | G43: =MARCH!M43 -> 800 | H43: =D43+E43+G43+F43 -> 10915 | I43: =10000+900 -> 10900 | J43: UD91V0CLJ6/UD91V0CXW7 | K43: 9/4/2026 | L43: APR | M43: =H43-I43 -> 15 | O43: SIGNED
A44: S20 | B44: PHELISIA | C44: 0718117097 | E44: 10100 | F44: 360 | G44: =MARCH!M44 -> -4791 | H44: =D44+E44+G44+F44 -> 5669 | I44: 3000 | J44: UDB2TOITZI | K44: 11/4/2026 | L44: APR | M44: =H44-I44 -> 2669 | O44: SIGNED
A45: S21 | B45: JOEL MAINA | C45: 0797262139 | E45: 10100 | F45: 465 | G45: =MARCH!M45 -> 100 | H45: =D45+E45+G45+F45 -> 10665 | I45: 10390 | J45: UD6OTBV6O5 | K45: 6/4/2026 | L45: APR | M45: =H45-I45 -> 275 | O45: SIGNED
A46: S22 | B46: JONA KIBET | C46: 0790405201 | E46: 10100 | F46: 870 | G46: =MARCH!M46 -> -111 | H46: =D46+E46+G46+F46 -> 10859 | I46: 10970 | J46: UD5QOBKH4 | K46: 46146 | L46: APR | M46: =H46-I46 -> -111 | O46: SIGNED
A47: S23 | B47: CINDY | C47: 0726239783 | E47: 10100 | F47: 15 | G47: =MARCH!M47 -> 0 | H47: =D47+E47+G47+F47 -> 10115 | I47: 10115 | J47: UD4LXBI6Q1 | K47: 46116 | L47: APR | M47: =H47-I47 -> 0
A48: S24 | B48: YASHON | C48: 0711167127 | E48: 10100 | F48: 150 | G48: =MARCH!M48 -> 0 | H48: =D48+E48+G48+F48 -> 10250 | I48: 10200 | J48: UD3I9BEKSI | K48: 3/4/2026 | L48: APR | M48: =H48-I48 -> 50 | O48: SIGNED
A49: S25 | B49: LIZZIE | C49: 0706359132 | E49: 10100 | F49: 300 | G49: =MARCH!M49 -> -125 | H49: =D49+E49+G49+F49 -> 10275 | I49: 10400 | J49: UD66VBPQB3 | K49: 46177 | L49: APR | M49: =H49-I49 -> -125
A50: S26 | B50: LUCY | C50: 0703357741 | E50: 10100 | F50: 240 | G50: =MARCH!M50 -> 0 | H50: =D50+E50+G50+F50 -> 10340 | I50: 10340 | J50: UD8950ASU8 | K50: 9/4/2026 | L50: APR | M50: =H50-I50 -> 0
A51: S27 | B51: DOROTHY | C51: 0793749115 | E51: 10100 | F51: 270 | G51: =MARCH!M51 -> -40 | H51: =D51+E51+G51+F51 -> 10330 | I51: 10370 | J51: UD3B1BKSN6 | K51: 46116 | L51: APR | M51: =H51-I51 -> -40 | O51: SIGNED
A52: S28 | B52: STELLA | C52: 0745586458 | E52: 10100 | F52: 30 | G52: =MARCH!M52 -> 100 | H52: =D52+E52+G52+F52 -> 10230 | I52: 10200 | J52: UD95G0HJKT | K52: 9/4/2026 | L52: APR | M52: =H52-I52 -> 30
A53: S29 | B53: JUMA | C53: 0702146655 | E53: 10100 | F53: 420 | G53: =MARCH!M53 -> -230 | H53: =D53+E53+G53+F53 -> 10290 | I53: 10520 | J53: UD4A2BQ81S | K53: 46116 | L53: APR | M53: =H53-I53 -> -230
A54: S30 | B54: JOSEPH MUGO | C54: 0704339161 | E54: 10100 | F54: 420 | G54: =MARCH!M54 -> -80 | H54: =D54+E54+G54+F54 -> 10440 | I54: 10520 | J54: UD5SB9RVOE | L54: APR | M54: =H54-I54 -> -80 | O54: SIGNED
A55: S31 | B55: DUNCAN | C55: 0723879509 | E55: 10100 | F55: 450 | G55: =MARCH!M55 -> 0 | H55: =D55+E55+G55+F55 -> 10550 | I55: 10000 | K55: 1ST APRIL | L55: APR | M55: =H55-I55 -> 550 | O55: SIGNED
A56: S32 | B56: EZEKIEL KAIKAI | C56: 0794799285 | E56: 9600 | F56: 615 | G56: =MARCH!M56 -> -10100 | H56: =D56+E56+G56+F56 -> 115 | I56: 10000 | J56: UCR9VAEQGQ | K56: 27/3/2026 | L56: APR | M56: =H56-I56 -> -9885 | O56: SIGNED
A57: Totals | E57: =SUM(E9:E56) -> 460000 | F57: =SUM(F9:F56) -> 18675 | G57: =SUM(G9:G56) -> -48152 | H57: =SUM(H9:H56) -> 430523 | I57: =SUM(I9:I56) -> 478100 | M57: =SUM(M9:M56) -> -47577
A59: Deductions
A60: Less Management fees | I60: =6%*I57 -> 28686
A61: PIPE RANGE
A62: TOTAL DEDUCTIONS | I62: =SUM(I60:I61) -> 28686
A64: BAL B/F | J64: Paid | L64: Paid | M64: Balance
A65: AMOUNT DUE | I65: =I62 -> 28686 | M65: =I65-J65-L65 -> 28686
A67: AUTHORISED BY JOSEPH GITHINJI | M67: 46142
E71: =I57/H57*100 -> 111.05098

Sheet MAY
C1: LOBBY ENTERPRISES
A2: PROPERTY MANAGERS AND ESTATE AGENTS
A3: MAY 2026
J4: P.O.BOX 11987
A5: STUDIO HAVEN | J5: TEL : 0722711933/4454322
A6: A/C | I6: Care taker | J6: ELIZABETH
I7: Phone no | J7: 0796292019
A8: HSE NO | B8: NAME | C8: PHONE NO | D8: DEPOSIT PAID | E8: MONTHLY RENT | F8: WATER BILL | G8: BAL B/D | H8: RENT DUE | I8: RENT PAID | J8: RCT NO | K8: DATE | L8: PERIOD | M8: BALANCE | N8: STATUS | O8: FORMS
A9: H1 | B9: ROSE | C9: 0707714065 | E9: 10100 | F9: 225 | G9: =APR!M9 -> 0 | H9: =D9+E9+G9+F9 -> 10325 | I9: 10325 | J9: UE6HM36AV2 | K9: 6/5/26 | L9: MAY | M9: =H9-I9 -> 0
A10: H2 | B10: BENSON | C10: 0741776284 | E10: 10100 | F10: 330 | G10: =APR!M10 -> 5 | H10: =D10+E10+G10+F10 -> 10435 | I10: 10450 | J10: UEBAY3R7F3 | K10: 11TH MAY | L10: MAY | M10: =H10-I10 -> -15 | O10: SIGNED
A11: H3 | B11: TESSA MARRIE | C11: 0716507709 | E11: 10100 | F11: 390 | G11: =APR!M11 -> -19795 | H11: =D11+E11+G11+F11 -> -9305 | L11: MAY | M11: =H11-I11 -> -9305
A12: H4 | B12: JOY | C12: 0724674470 | E12: 10100 | F12: 0 | G12: 0 | H12: =D12+E12+G12+F12 -> 10100 | I12: =5000+5000 -> 10000 | J12: UEJOH4KMRT | K12: 6TH MAY | L12: MAY | M12: =H12-I12 -> 100 | N12: MOVED IN 19TH MAY | O12: SIGNED
A13: H5 | B13: PAUL | C13: 0723316248 | E13: 10100 | F13: 180 | G13: =APR!M13 -> 995 | H13: =D13+E13+G13+F13 -> 11275 | I13: 10000 | J13: UE5OF3BU7X | K13: 5TH MAY | L13: MAY | M13: =H13-I13 -> 1275 | O13: SIGNED
A14: H6 | B14: MARY MESUSWA | D14: 5000 | E14: 10100 | G14: =APR!M14 -> 0 | H14: =D14+E14+G14+F14 -> 15100 | I14: 15000 | J14: UEGCXP337 | K14: 16TH MAY | L14: MAY | M14: =H14-I14 -> 100 | N14: MOVED IN 29TH MAY
A15: H7 | B15: MUNYIRI WACHIRA | C15: 0700935843 | D15: 10000 | E15: 10100 | F15: 0 | G15: 0 | H15: =D15+E15+G15+F15 -> 20100 | I15: =20100+10250 -> 30350 | J15: UIE6OF3G5A1/UEMOF57ICS | K15: 6TH MAY | L15: MAY | M15: =H15-I15 -> -10250 | N15: MOVED IN 1ST MAY
A16: H8 | B16: BONIFACE | C16: 0703962575 | E16: 12100 | F16: 675 | G16: =APR!M16 -> 0 | H16: =D16+E16+G16+F16 -> 12775 | I16: 12765 | K16: 07.05.2026 | L16: MAY | M16: =H16-I16 -> 10 | O16: SIGNED | S16: 12765 | T16: 7TH MAY
A17: H9 | B17: ROBERT | C17: 0726405930 | E17: 14100 | F17: 1875 | G17: =APR!M17 -> -5975 | H17: =D17+E17+G17+F17 -> 10000 | I17: 15000 | J17: UDU132H7744 | K17: 30/4/26 | L17: MAY | M17: =H17-I17 -> -5000
A18: H10 | B18: BEATRICE | C18: 0711729058 | E18: 10100 | F18: 660 | G18: =APR!M18 -> 200 | H18: =D18+E18+G18+F18 -> 10960 | I18: 10600 | J18: UE5RI33TBL | K18: 5TH MAY | L18: MAY | M18: =H18-I18 -> 360 | O18: SIGNED
A19: H11 | B19: PETER | C19: 0708568404 | E19: 10100 | F19: 165 | G19: =APR!M19 -> 0 | H19: =D19+E19+G19+F19 -> 10265 | I19: 10160 | J19: UFK86Q6JY | K19: 5/5/26 | L19: MAY | M19: =H19-I19 -> 105
A20: H12 | B20: GIDEON | C20: 0712026963 | E20: 10100 | F20: 270 | G20: =APR!M20 -> 0 | H20: =D20+E20+G20+F20 -> 10370 | I20: 10370 | J20: UE9953N520 | K20: 9/5/26 | L20: MAY | M20: =H20-I20 -> 0 | O20: SIGNED
A21: H13 | B21: SHAWN RATEMO | C21: 0716484383/'0721832745 | E21: 10100 | F21: 480 | G21: =APR!M21 -> 275 | H21: =D21+E21+G21+F21 -> 10855 | I21: 10500 | J21: UEB7V46U9U | K21: 11TH MAY | L21: MAY | M21: =H21-I21 -> 355 | O21: SIGNED
A22: H14 | B22: SAID A SAID | C22: 0719488891 | E22: 10100 | F22: 810 | G22: =APR!M22 -> -375 | H22: =D22+E22+G22+F22 -> 10535 | I22: 10950 | J22: UE625353TF | K22: 6TH MAY | L22: MAY | M22: =H22-I22 -> -415 | O22: SIGNED
A23: H15 | B23: RONO ELIJAH | C23: 0745935239 | E23: 10100 | F23: 915 | G23: =APR!M23 -> 4210 | H23: =D23+E23+G23+F23 -> 15225 | I23: 11000 | J23: UDU1F2P1I4 | K23: 30TH APRIL | L23: MAY | M23: =H23-I23 -> 4225 | O23: SIGNED
A24: H16 | B24: KELVIN GITONGA | C24: 0792391382 | E24: 10100 | F24: 315 | G24: =APR!M24 -> -105 | H24: =D24+E24+G24+F24 -> 10310 | I24: 10415 | J24: UE6R42V86S | K24: 6/5/26 | L24: MAY | M24: =H24-I24 -> -105 | O24: SIGNED | P24: CR | Q24: =I57/H57*100 -> 108.48069
A25: S1 | B25: VIVIAN | C25: 0748596476 | E25: 10100 | F25: 480 | G25: =APR!M25 -> 74 | H25: =D25+E25+G25+F25 -> 10654 | I25: 10340 | J25: UE71A3FDTW | K25: 9TH MAY | L25: MAY | M25: =H25-I25 -> 314 | O25: SIGNED
A26: S2 | B26: LINDA | C26: 0748689851 | E26: 10100 | F26: 105 | G26: =APR!M26 -> 0 | H26: =D26+E26+G26+F26 -> 10205 | I26: 10205 | J26: UE55V38ZM8 | K26: 46147 | L26: MAY | M26: =H26-I26 -> 0 | O26: SIGNED
A27: S3 | B27: WARREN | C27: 0769883948 | E27: 10100 | F27: 480 | G27: =APR!M27 -> -680 | H27: =D27+E27+G27+F27 -> 9900 | I27: 10580 | J27: UA69R3DX27 | K27: 6TH MAY | L27: MAY | M27: =H27-I27 -> -680 | O27: SIGNED
A28: S4 | B28: SCOLA | C28: 0793889379 | E28: 10100 | F28: 105 | G28: =APR!M28 -> 75 | H28: =D28+E28+G28+F28 -> 10280 | I28: 10105 | J28: UEBHE3VSIH | K28: 11TH MAY | L28: MAY | M28: =H28-I28 -> 175 | P28: CR | Q28: 75.570748
A29: S5 | B29: CARETAKER | G29: =APR!M29 -> 0 | H29: =D29+E29+G29+F29 -> 0 | L29: MAY | M29: =H29-I29 -> 0
A30: S6 | B30: IMELDA | C30: 0723500330 | E30: 10100 | F30: 180 | G30: =APR!M30 -> 70 | H30: =D30+E30+G30+F30 -> 10350 | I30: 10300 | J30: UE4D33450Z | K30: 4/5/26 | L30: MAY | M30: =H30-I30 -> 50 | O30: SIGNED | P30: 2 BROKEN PADLOCK ADD 1000
A31: S7 | B31: EVANS | C31: 0702377661 | E31: 10100 | F31: 0 | G31: =APR!M31 -> -8 | H31: =D31+E31+G31+F31 -> 10092 | I31: 10100 | J31: UE5J430PJ8 | K31: 5TH MAY | L31: MAY | M31: =H31-I31 -> -8
A32: S8 | B32: BRIAN CHERUIYOT | C32: 0746324500 | E32: 10100 | F32: 510 | G32: =APR!M32 -> 40 | H32: =D32+E32+G32+F32 -> 10650 | I32: 10000 | J32: UEG7Q4QTGM | K32: 16TH MAY | L32: MAY | M32: =H32-I32 -> 650 | O32: SIGNED
A33: S9 | B33: DORCAS KENANDA | C33: 0723433108 | E33: 10100 | F33: 165 | G33: =APR!M33 -> -170 | H33: =D33+E33+G33+F33 -> 10095 | I33: 10250 | J33: UE4473L55T | K33: 4TH MAY | L33: MAY | M33: =H33-I33 -> -155 | O33: SIGNED
A34: S10 | B34: MONICAH | C34: 0740454928 | E34: 10100 | F34: 195 | G34: =APR!M34 -> 100 | H34: =D34+E34+G34+F34 -> 10395 | I34: 10295 | J34: UECSG0CXXY | K34: 12/5/26 | L34: MAY | M34: =H34-I34 -> 100
A35: S11 | B35: IAN KAMAU | C35: 0745292688 | E35: 10100 | F35: 120 | G35: =APR!M35 -> -10430 | H35: =D35+E35+G35+F35 -> -210 | L35: MAY | M35: =H35-I35 -> -210
A36: S12 | B36: JUSTINE | C36: 0724282631 | E36: 10100 | F36: 45 | G36: =APR!M36 -> -10205 | H36: =D36+E36+G36+F36 -> -60 | I36: 10300 | J36: Y3LUKJZ5XFV | K36: 1/5/26 | L36: MAY | M36: =H36-I36 -> -10360
A37: S13 | B37: DERRICK | C37: 0707280087 | E37: 10100 | F37: 240 | G37: =APR!M37 -> -25 | H37: =D37+E37+G37+F37 -> 10315 | I37: 10340 | J37: UE7IA3FDTW | K37: 7TH MAY | L37: MAY | M37: =H37-I37 -> -25
A38: S14 | B38: VINCENT | C38: 0798467289 | E38: 10100 | F38: 195 | G38: =APR!M38 -> 315 | H38: =D38+E38+G38+F38 -> 10610 | I38: 10415 | J38: UDO191U64J | K38: 24TH APRIL | L38: MAY | M38: =H38-I38 -> 195
A39: S15 | B39: ARON | C39: 0706195266 | E39: 10100 | F39: 255 | G39: =APR!M39 -> 200 | H39: =D39+E39+G39+F39 -> 10555 | I39: 10255 | J39: UE65Q3S7TI | K39: 6TH MAY | L39: MAY | M39: =H39-I39 -> 300 | O39: SIGNED
A40: S16 | B40: BEN SAKWA | C40: 0725451845 | E40: 10100 | F40: 1245 | G40: =APR!M40 -> 0 | H40: =D40+E40+G40+F40 -> 11345 | I40: =10100+1245 -> 11345 | J40: UDO2A2FJX2 | K40: 24TH APRIL | L40: MAY | M40: =H40-I40 -> 0 | O40: SIGNED
A41: S17 | B41: ANNE RITA | D41: 10000 | E41: 10100 | G41: =APR!M41 -> 0 | H41: =D41+E41+G41+F41 -> 20100 | I41: =10000+5000 -> 15000 | J41: UER4A6HDTL/REF | K41: 27TH MAY | L41: MAY | M41: =H41-I41 -> 5100 | N41: MOVED IN 1ST JUNE | O41: SIGNED
A42: S18 | B42: LIZZIE NYAMBURA | C42: 0792838695 | E42: 10100 | F42: 375 | G42: =APR!M42 -> -52 | H42: =D42+E42+G42+F42 -> 10423 | I42: 10375 | J42: UE56L379EV | K42: 5TH MAY | L42: MAY | M42: =H42-I42 -> 48 | O42: SIGNED
A43: S19 | B43: LINAH WAITHIRA NDERU | C43: 0786286496 | E43: 10100 | F43: 90 | G43: =APR!M43 -> 15 | H43: =D43+E43+G43+F43 -> 10205 | I43: 10000 | J43: UE81V3PQJQ | K43: 9/5/26 | L43: MAY | M43: =H43-I43 -> 205 | O43: SIGNED
A44: S20 | B44: PHELISIA | C44: 0718117097 | E44: 10100 | F44: 840 | G44: =APR!M44 -> 2669 | H44: =D44+E44+G44+F44 -> 13609 | I44: 14815 | J44: UEB2T3Y0S9 | K44: 11TH MAY | L44: MAY | M44: =H44-I44 -> -1206 | N44: POWER OFF | O44: SIGNED
A45: S21 | B45: JOEL MAINA | C45: 0797262139 | E45: 10100 | F45: 420 | G45: =APR!M45 -> 275 | H45: =D45+E45+G45+F45 -> 10795 | I45: =16815+10510 -> 27325 | J45: UE71X30OTG | K45: 7TH MAY/13JUNE | L45: MAY | M45: =H45-I45 -> -16530 | O45: SIGNED
A46: S22 | B46: JONA KIBET | C46: 0790405201 | E46: 10100 | F46: 765 | G46: =APR!M46 -> -111 | H46: =D46+E46+G46+F46 -> 10754 | I46: 10865 | J46: UE5QO31QAG | K46: 5/5/26 | L46: MAY | M46: =H46-I46 -> -111 | O46: SIGNED
A47: S23 | B47: CINDY | C47: 0726239783 | E47: 10100 | F47: 60 | G47: =APR!M47 -> 0 | H47: =D47+E47+G47+F47 -> 10160 | I47: 10100 | J47: UE4LX2VJQF | K47: 46147 | L47: MAY | M47: =H47-I47 -> 60
A48: S24 | B48: YASHON | C48: 0711167127 | E48: 10100 | F48: 105 | G48: =APR!M48 -> 50 | H48: =D48+E48+G48+F48 -> 10255 | I48: 10205 | J48: UE7I93E3FD | K48: 7/4/26 | L48: MAY | M48: =H48-I48 -> 50 | O48: SIGNED
A49: S25 | B49: LIZZIE | C49: 0706359132 | E49: 10100 | F49: 300 | G49: =APR!M49 -> -125 | H49: =D49+E49+G49+F49 -> 10275 | I49: 10100 | J49: UE6I74E2FD | K49: 46331 | L49: MAY | M49: =H49-I49 -> 175
A50: S26 | B50: LUCY | C50: 0703357741 | E50: 10100 | F50: 165 | G50: =APR!M50 -> 0 | H50: =D50+E50+G50+F50 -> 10265 | I50: 10265 | J50: UE9853RN8M | K50: 9/4/26 | L50: MAY | M50: =H50-I50 -> 0
A51: S27 | B51: DOROTHY | C51: 0793749115 | E51: 10100 | F51: 330 | G51: =APR!M51 -> -40 | H51: =D51+E51+G51+F51 -> 10390 | I51: 10430 | J51: UE4B13A09F | K51: 4/5/26 | L51: MAY | M51: =H51-I51 -> -40 | O51: SIGNED
A52: S28 | B52: STELLA | C52: 0745586458 | E52: 10100 | F52: 0 | G52: =APR!M52 -> 30 | H52: =D52+E52+G52+F52 -> 10130 | I52: 10100 | J52: UEA5G43PTH | K52: 10/5/26 | L52: MAY | M52: =H52-I52 -> 30
A53: S29 | B53: JUMA | C53: 0702146655 | E53: 10100 | F53: 300 | G53: =APR!M53 -> -230 | H53: =D53+E53+G53+F53 -> 10170 | I53: 10400 | J53: UE7A23OYM7 | K53: 7TH MAY | L53: MAY | M53: =H53-I53 -> -230
A54: S30 | B54: JOSEPH MUGO | C54: 0704339161 | E54: 10100 | F54: 330 | G54: =APR!M54 -> -80 | H54: =D54+E54+G54+F54 -> 10350 | I54: 10430 | J54: UE6SBB4FKJ | K54: 6/5/26 | L54: MAY | M54: =H54-I54 -> -80 | O54: SIGNED
A55: S31 | B55: DUNCAN | C55: 0723879509 | E55: 10100 | F55: 285 | G55: =APR!M55 -> 550 | H55: =D55+E55+G55+F55 -> 10935 | I55: 10300 | J55: UE1C430RAK | K55: 1ST MAY | L55: MAY | M55: =H55-I55 -> 635 | O55: SIGNED
A56: S32 | B56: EZEKIEL KAIKAI | C56: 0794799285 | E56: 9600 | F56: 255 | G56: =APR!M56 -> -9885 | H56: =D56+E56+G56+F56 -> -30 | L56: MAY | M56: =H56-I56 -> -30 | O56: SIGNED
A57: Totals | E57: =SUM(E9:E56) -> 480200 | F57: =SUM(F9:F56) -> 16230 | G57: =SUM(G9:G56) -> -48143 | H57: =SUM(H9:H56) -> 473287 | I57: =SUM(I9:I56) -> 513425 | M57: =SUM(M9:M56) -> -40138
A59: Deductions
A60: Less Management fees | I60: =6%*I57 -> 30805.5
A61: KARANJA WAGE& MOBILIZATION/ROOFING NAILS/SILICONE | I61: =1500+600 -> 2100
A62: TOTAL DEDUCTIONS | I62: =SUM(I60:I61) -> 32905.5
A64: BAL B/F | J64: Paid | L64: Paid | M64: Balance
A65: AMOUNT DUE | I65: =I62 -> 32905.5 | M65: =I65-J65-L65 -> 32905.5
A67: AUTHORISED BY JOSEPH GITHINJI | M67: 46173
E71: =I57/H57*100 -> 108.48069

Sheet JUNE
C1: LOBBY ENTERPRISES
A2: PROPERTY MANAGERS AND ESTATE AGENTS
A3: JUNE 2026
J4: P.O.BOX 11987
A5: STUDIO HAVEN | J5: TEL : 0722711933/4454322
A6: A/C | I6: Care taker | J6: ELIZABETH
I7: Phone no | J7: 0796292019
A8: HSE NO | B8: NAME | C8: PHONE NO | D8: DEPOSIT PAID | E8: MONTHLY RENT | F8: WATER BILL | G8: BAL B/D | H8: RENT DUE | I8: RENT PAID | J8: RCT NO | K8: DATE | L8: PERIOD | M8: BALANCE | N8: STATUS | O8: FORMS
A9: H1 | B9: ROSE | C9: 0707714065 | E9: 10100 | F9: 660 | G9: =MAY!M9 -> 0 | H9: =D9+E9+G9+F9 -> 10760 | I9: 10760 | J9: UF4HM6FIAG | K9: 46118 | L9: JUNE | M9: =H9-I9 -> 0
A10: H2 | B10: BENSON | C10: 0741776284 | E10: 10100 | F10: 675 | G10: =MAY!M10 -> -15 | H10: =D10+E10+G10+F10 -> 10760 | I10: 10775 | J10: UFAAY7348Q | K10: 46301 | L10: JUNE | M10: =H10-I10 -> -15 | O10: SIGNED
A11: H3 | B11: TESSA MARRIE | C11: 0716507709 | E11: 10100 | F11: 300 | G11: =MAY!M11 -> -9305 | H11: =D11+E11+G11+F11 -> 1095 | L11: JUNE | M11: =H11-I11 -> 1095
A12: H4 | B12: JOY | C12: 0724674470 | E12: 10100 | F12: 255 | G12: =MAY!M12 -> 100 | H12: =D12+E12+G12+F12 -> 10455 | I12: 10000 | J12: UFEOH7KPRZ | K12: 14/6/26 | L12: JUNE | M12: =H12-I12 -> 455 | O12: SIGNED
A13: H5 | B13: PAUL | C13: 0723316248 | E13: 10100 | F13: 735 | G13: =MAY!M13 -> 1275 | H13: =D13+E13+G13+F13 -> 12110 | I13: 10000 | J13: UF5OF6RML6 | K13: 5/6/26 | L13: JUNE | M13: =H13-I13 -> 2110 | O13: SIGNED
A14: H6 | B14: MARY MESUSWA | C14: 0757079026 | E14: 10100 | F14: 720 | G14: =MAY!M14 -> 100 | H14: =D14+E14+G14+F14 -> 10920 | I14: 10000 | J14: UF4PY6FO4F | K14: 5/6/26 | L14: JUNE | M14: =H14-I14 -> 920
A15: H7 | B15: MUNYIRI WACHIRA | C15: 0700935843 | E15: 10100 | F15: 0 | G15: =MAY!M15 -> -10250 | H15: =D15+E15+G15+F15 -> -150 | I15: 10000 | J15: UFJLO814KP | K15: 46148 | L15: JUNE | M15: =H15-I15 -> -10150
A16: H8 | B16: BONIFACE | C16: 0703962575 | E16: 12100 | F16: 1155 | G16: =MAY!M16 -> 10 | H16: =D16+E16+G16+F16 -> 13265 | I16: 13215 | J16: UF52M6Z9CY | K16: 5/6/26 | L16: JUNE | M16: =H16-I16 -> 50 | O16: SIGNED
A17: H9 | B17: ROBERT | C17: 0726405930 | E17: 14100 | F17: 1500 | G17: =MAY!M17 -> -5000 | H17: =D17+E17+G17+F17 -> 10600 | I17: 10600 | J17: UF64J7V7BT | K17: 46183 | L17: JUNE | M17: =H17-I17 -> 0
A18: H10 | B18: BEATRICE | C18: 0711729058 | E18: 10100 | F18: 1065 | G18: =MAY!M18 -> 360 | H18: =D18+E18+G18+F18 -> 11525 | I18: 11065 | J18: UF9RI75SSE | K18: 46271 | L18: JUNE | M18: =H18-I18 -> 460 | O18: SIGNED
A19: H11 | B19: PETER | C19: 0708568404 | E19: 10100 | F19: 60 | G19: =MAY!M19 -> 105 | H19: =D19+E19+G19+F19 -> 10265 | I19: 10160 | J19: UF5K86Q6JY | K19: 5/6/26 | L19: JUNE | M19: =H19-I19 -> 105
A20: H12 | B20: GIDEON | C20: 0712026963 | E20: 10100 | F20: 450 | G20: =MAY!M20 -> 0 | H20: =D20+E20+G20+F20 -> 10550 | I20: 10550 | J20: UF6956V43Z | K20: 6/6/26 | L20: JUNE | M20: =H20-I20 -> 0 | O20: SIGNED
A21: H13 | B21: SHAWN RATEMO | C21: 0716484383/'0721832745 | E21: 10100 | F21: 645 | G21: =MAY!M21 -> 355 | H21: =D21+E21+G21+F21 -> 11100 | I21: 10700 | J21: UF7V7F0G9 | K21: 8/6/26 | L21: JUNE | M21: =H21-I21 -> 400 | O21: SIGNED
A22: H14 | B22: SAID A SAID | C22: 0719488891 | E22: 10100 | F22: 270 | G22: =MAY!M22 -> -415 | H22: =D22+E22+G22+F22 -> 9955 | I22: =10080+230+100 -> 10410 | J22: UF75K76FE5 | K22: 7/6/26 | L22: JUNE | M22: =H22-I22 -> -455 | O22: SIGNED
A23: H15 | B23: RONO ELIJAH | C23: 0745935239 | E23: 10100 | F23: 1155 | G23: =MAY!M23 -> 4225 | H23: =D23+E23+G23+F23 -> 15480 | I23: 10255 | J23: UE653S7TI | K23: 46178 | L23: JUNE | M23: =H23-I23 -> 5225 | O23: SIGNED
A24: H16 | B24: KELVIN GITONGA | C24: 0792391382 | E24: 10100 | F24: 780 | G24: =MAY!M24 -> -105 | H24: =D24+E24+G24+F24 -> 10775 | I24: 10880 | J24: UF5R46BAW7 | K24: 5/6/26 | L24: JUNE | M24: =H24-I24 -> -105 | O24: SIGNED | P24: CR | Q24: =I57/H57*100 -> 106.64689
A25: S1 | B25: VIVIAN | C25: 0748596476 | E25: 10100 | F25: 735 | G25: =MAY!M25 -> 314 | H25: =D25+E25+G25+F25 -> 11149 | I25: 10480 | J25: UE9KD3M6TM | L25: JUNE | M25: =H25-I25 -> 669 | O25: SIGNED
A26: S2 | B26: LINDA | C26: 0748689851 | E26: 10100 | F26: 150 | G26: =MAY!M26 -> 0 | H26: =D26+E26+G26+F26 -> 10250 | I26: 10250 | J26: UF65V6X8RL | K26: 6/6/26 | L26: JUNE | M26: =H26-I26 -> 0 | O26: SIGNED
A27: S3 | B27: WARREN | C27: 0769883948 | E27: 10100 | F27: 615 | G27: =MAY!M27 -> -680 | H27: =D27+E27+G27+F27 -> 10035 | I27: 10715 | J27: UF59R6TF1F | K27: 5/6/26 | L27: JUNE | M27: =H27-I27 -> -680 | O27: SIGNED
A28: S4 | B28: SCOLA | C28: 0793889379 | E28: 10100 | F28: 420 | G28: =MAY!M28 -> 175 | H28: =D28+E28+G28+F28 -> 10695 | I28: 20000 | J28: 20000 | K28: 46213 | L28: JUNE | M28: =H28-I28 -> -9305 | P28: CR | Q28: 75.570748
A29: S5 | B29: CARETAKER | G29: =MAY!M29 -> 0 | H29: =D29+E29+G29+F29 -> 0 | L29: JUNE | M29: =H29-I29 -> 0
A30: S6 | B30: IMELDA | C30: 0723500330 | E30: 10100 | F30: 255 | G30: =MAY!M30 -> 50 | H30: =D30+E30+G30+F30 -> 10405 | I30: 10300 | J30: UF7D37OJMW | K30: 7/6/26 | L30: JUNE | M30: =H30-I30 -> 105 | O30: SIGNED | P30: 2 BROKEN PADLOCK ADD 1000
A31: S7 | B31: EVANS | C31: 0702377661 | E31: 10100 | F31: 30 | G31: =MAY!M31 -> -8 | H31: =D31+E31+G31+F31 -> 10122 | I31: 10130 | J31: UF6RP6ZWZE | K31: 6/6/26 | L31: JUNE | M31: =H31-I31 -> -8
A32: S8 | B32: BRIAN CHERUIYOT | C32: 0746324500 | E32: 10100 | F32: 1635 | G32: =MAY!M32 -> 650 | H32: =D32+E32+G32+F32 -> 12385 | I32: 11000 | J32: UFE7Q87L0Y | K32: 14/6/26 | L32: JUNE | M32: =H32-I32 -> 1385 | O32: SIGNED
A33: S9 | B33: DORCAS KENANDA | C33: 0723433108 | E33: 10100 | F33: 225 | G33: =MAY!M33 -> -155 | H33: =D33+E33+G33+F33 -> 10170 | I33: 10325 | L33: JUNE | M33: =H33-I33 -> -155 | O33: SIGNED
A34: S10 | B34: MONICAH | C34: 0740454928 | E34: 10100 | F34: 210 | G34: =MAY!M34 -> 100 | H34: =D34+E34+G34+F34 -> 10410 | I34: 10300 | J34: UF5LR6BG7L | K34: 5/6/26 | L34: JUNE | M34: =H34-I34 -> 110
A35: S11 | B35: IAN KAMAU | C35: 0745292688 | E35: 10100 | F35: 165 | G35: =MAY!M35 -> -210 | H35: =D35+E35+G35+F35 -> 10055 | I35: 10385 | J35: UF5MS6R260 | K35: 46147 | L35: JUNE | M35: =H35-I35 -> -330
A36: S12 | B36: JUSTINE | C36: 0724282631 | E36: 10100 | F36: 165 | G36: =MAY!M36 -> -10360 | H36: =D36+E36+G36+F36 -> -95 | I36: 10200 | J36: 63N8KEDMMC5 | K36: 46148 | L36: JUNE | M36: =H36-I36 -> -10295
A37: S13 | B37: DERRICK | C37: 0707280087 | E37: 10100 | F37: 300 | G37: =MAY!M37 -> -25 | H37: =D37+E37+G37+F37 -> 10375 | I37: 10400 | J37: UF81A7357T | K37: ..'8/6/26 | L37: JUNE | M37: =H37-MAY!I25 -> 35
A38: S14 | B38: VINCENT | C38: 0798467289 | E38: 10100 | F38: 435 | G38: =MAY!M38 -> 195 | H38: =D38+E38+G38+F38 -> 10730 | I38: 10295 | J38: UER195IQ02 | K38: 27/5/26 | L38: JUNE | M38: =H38-I38 -> 435
A39: S15 | B39: ARON | C39: 0706195266 | E39: 10100 | F39: 150 | G39: =MAY!M39 -> 300 | H39: =D39+E39+G39+F39 -> 10550 | I39: 10255 | J39: UE65Q33S7TI | K39: 24/6/26 | L39: JUNE | M39: =H39-I39 -> 295 | O39: SIGNED
A40: S16 | B40: BEN SAKWA | C40: 0725451845 | E40: 10100 | F40: 1650 | G40: =MAY!M40 -> 0 | H40: =D40+E40+G40+F40 -> 11750 | I40: 10100 | J40: UEP4861MFO | K40: 25/5/26 | L40: JUNE | M40: =H40-I40 -> 1650 | O40: SIGNED
A41: S17 | B41: DENNIS OWINO | C41: 0712299080 | E41: 10100 | F41: 0 | G41: 0 | H41: =D41+E41+G41+F41 -> 10100 | I41: 10000 | J41: UF1IE6FG0D | K41: 1/6/26 | L41: JUNE | M41: =H41-I41 -> 100 | O41: SIGNED
A42: S18 | B42: LIZZIE NYAMBURA | C42: 0792838695 | E42: 10100 | F42: 360 | G42: =MAY!M42 -> 48 | H42: =D42+E42+G42+F42 -> 10508 | I42: 10360 | J42: UF56L6Q8TD | K42: 5/6/26 | L42: JUNE | M42: =H42-I42 -> 148 | O42: SIGNED
A43: S19 | B43: LINAH WAITHIRA NDERU | C43: 0786286496 | E43: 10100 | F43: 120 | G43: =MAY!M43 -> 205 | H43: =D43+E43+G43+F43 -> 10425 | I43: =10100+120 -> 10220 | J43: UF9IV7DYVG | K43: 46271 | L43: JUNE | M43: =H43-I43 -> 205 | O43: SIGNED
A44: S20 | B44: PHELISIA | C44: 0718117097 | E44: 10100 | F44: 690 | G44: =MAY!M44 -> -1206 | H44: =D44+E44+G44+F44 -> 9584 | I44: =7000+2000 -> 9000 | J44: UF52T6NYNP/UF2T84LTU | K44: 5/6/26/19TH JUNE | L44: JUNE | M44: =H44-I44 -> 584 | O44: SIGNED
A45: S21 | B45: JOEL MAINA | C45: 0797262139 | E45: 10100 | F45: 510 | G45: =MAY!M45 -> -16530 | H45: =D45+E45+G45+F45 -> -5920 | I45: 10510 | J45: UF8OT7CSVQ | K45: 8/6/26 | L45: JUNE | M45: =H45-I45 -> -16430 | O45: SIGNED
A46: S22 | B46: JONA KIBET | C46: 0790405201 | E46: 10100 | F46: 915 | G46: =MAY!M46 -> -111 | H46: =D46+E46+G46+F46 -> 10904 | I46: 11015 | J46: UF4QO6EDDE | K46: 46118 | L46: JUNE | M46: =H46-I46 -> -111 | O46: SIGNED
A47: S23 | B47: CINDY | C47: 0726239783 | E47: 10100 | F47: 90 | G47: =MAY!M47 -> 60 | H47: =D47+E47+G47+F47 -> 10250 | I47: 10160 | J47: UF2LX684RS | K47: 46059 | L47: JUNE | M47: =H47-I47 -> 90
A48: S24 | B48: YASHON | C48: 0711167127 | E48: 10100 | F48: 150 | G48: =MAY!M48 -> 50 | H48: =D48+E48+G48+F48 -> 10300 | I48: 10200 | J48: UF319D8JQ | K48: 46087 | L48: JUNE | M48: =H48-I48 -> 100 | O48: SIGNED
A49: S25 | B49: LIZZIE | C49: 0706359132 | E49: 10100 | F49: 360 | G49: =MAY!M49 -> 175 | H49: =D49+E49+G49+F49 -> 10635 | I49: 10460 | J49: UF5U908YXY | K49: 6/6/26 | L49: JUNE | M49: =H49-I49 -> 175
A50: S26 | B50: LUCY | C50: 0703357741 | E50: 10100 | F50: 240 | G50: =MAY!M50 -> 0 | H50: =D50+E50+G50+F50 -> 10340 | I50: 10350 | J50: UF8857ABBD | K50: 8/6/26 | L50: JUNE | M50: =H50-I50 -> -10
A51: S27 | B51: DOROTHY | C51: 0793749115 | E51: 10100 | F51: 240 | G51: =MAY!M51 -> -40 | H51: =D51+E51+G51+F51 -> 10300 | I51: =10340 -> 10340 | J51: UF4B16RRQR | K51: 4TH JUNE | L51: JUNE | M51: =H51-I51 -> -40 | O51: SIGNED
A52: S28 | B52: STELLA | C52: 0745586458 | E52: 10100 | F52: 0 | G52: =MAY!M52 -> 30 | H52: =D52+E52+G52+F52 -> 10130 | I52: 10100 | J52: UF85G7FOUS | K52: 8/6/26 | L52: JUNE | M52: =H52-I52 -> 30
A53: S29 | B53: JUMA | C53: 0702146655 | E53: 10100 | F53: 675 | G53: =MAY!M53 -> -230 | H53: =D53+E53+G53+F53 -> 10545 | I53: 10100 | J53: UF85G7FOUS | K53: 46240 | L53: JUNE | M53: =H53-I53 -> 445
A54: S30 | B54: JOSEPH MUGO | C54: 0704339161 | E54: 10100 | F54: 465 | G54: =MAY!M54 -> -80 | H54: =D54+E54+G54+F54 -> 10485 | I54: 10565 | J54: UFSBOJM8O | K54: 5/6/26 | L54: JUNE | M54: =H54-I54 -> -80 | O54: SIGNED
A55: S31 | B55: TIMOTHU KURIA | C55: 0797778633 | E55: 10100 | F55: 0 | H55: =D55+E55+G55+F55 -> 10100 | I55: 10000 | J55: UE56L6Q8TD | K55: 5/6/26 | L55: JUNE | M55: =H55-I55 -> 100 | N55: NEW TENANT | O55: SIGNED
A56: S32 | B56: MRENJE CHRISANTHUS | C56: 0794033100 | E56: 10100 | F56: 240 | H56: =D56+E56+G56+F56 -> 10340 | I56: 10000 | K56: 29/5/26 | L56: JUNE | M56: =H56-I56 -> 340 | O56: SIGNED
A57: Totals | E57: =SUM(E9:E56) -> 480700 | F57: =SUM(F9:F56) -> 22620 | G57: =SUM(G9:G56) -> -45843 | H57: =SUM(H9:H56) -> 457477 | I57: =SUM(I9:I56) -> 487885 | M57: =SUM(M9:M56) -> -30348
A59: Deductions
A60: Less Management fees | I60: =6%*I57 -> 29273.1
A61: TOTAL DEDUCTIONS | I61: =SUM(I60:I60) -> 29273.1
A63: BAL B/F | I63: =MAY!M65 -> 32905.5 | J63: Paid | L63: Paid | M63: Balance
A64: AMOUNT DUE | I64: =I61 -> 29273.1 | M64: =I64-J64-L64 -> 29273.1
A66: AUTHORISED BY JOSEPH GITHINJI | M66: 46203
E70: =I57/H57*100 -> 106.64689

Sheet JULY
C1: LOBBY ENTERPRISES
A2: PROPERTY MANAGERS AND ESTATE AGENTS
A3: JULY 2026
J4: P.O.BOX 11987
A5: STUDIO HAVEN | J5: TEL : 0722711933/4454322
A6: A/C | I6: Care taker | J6: ELIZABETH
I7: Phone no | J7: 0796292019
A8: HSE NO | B8: NAME | C8: PHONE NO | D8: DEPOSIT PAID | E8: MONTHLY RENT | F8: WATER BILL | G8: BAL B/D | H8: RENT DUE | I8: RENT PAID | J8: RCT NO | K8: DATE | L8: PERIOD | M8: BALANCE | N8: STATUS | O8: FORMS
A9: H1 | B9: ROSE | C9: 0707714065 | E9: 10100 | F9: 315 | G9: =JUNE!M9 -> 0 | H9: =D9+E9+G9+F9 -> 10415 | I9: =10415 -> 10415 | J9: UG2HM9QX0V | K9: 02/072026 | L9: JULY | M9: =H9-I9 -> 0
A10: H2 | B10: BENSON | C10: 0741776284 | E10: 10100 | F10: 270 | G10: =JUNE!M10 -> -15 | H10: =D10+E10+G10+F10 -> 10355 | I10: =10300 -> 10300 | J10: UG5BDP7VVQ | K10: 05.07.2026 | L10: JULY | M10: =H10-I10 -> 55 | O10: SIGNED
A11: H3 | B11: TESSA MARRIE | C11: 0716507709 | E11: 10100 | F11: 225 | G11: =JUNE!M11 -> 1095 | H11: =D11+E11+G11+F11 -> 11420 | I11: 10325 | J11: UG9OVAY5XZ | K11: 46211 | L11: JULY | M11: =H11-I11 -> 1095
A12: H4 | B12: JOY | C12: 0724674470 | E12: 10100 | F12: 210 | G12: =JUNE!M12 -> 455 | H12: =D12+E12+G12+F12 -> 10765 | I12: 15410 | J12: UG6OHA3B8A | K12: 46209 | L12: JULY | M12: =H12-I12 -> -4645 | O12: SIGNED
A13: H5 | B13: PAUL | C13: 0723316248 | E13: 10100 | F13: 750 | G13: =JUNE!M13 -> 2110 | H13: =D13+E13+G13+F13 -> 12960 | L13: JULY | M13: =H13-I13 -> 12960 | O13: SIGNED | S13: 12774 4th july
A14: H6 | B14: MARY MESUSWA | C14: 0757079026 | E14: 10100 | F14: 285 | G14: =JUNE!M14 -> 920 | H14: =D14+E14+G14+F14 -> 11305 | I14: =10325+10480 -> 20805 | J14: UG3OVAY4XZ / UGVPY0Z9AA | K14: 09.07.2026/31.07.2026 | L14: JULY | M14: =H14-I14 -> -9500
A15: H7 | B15: MUNYIRI WACHIRA | C15: 0700935843 | E15: 10100 | F15: 15 | G15: =JUNE!M15 -> -10150 | H15: =D15+E15+G15+F15 -> -35 | I15: =10000 -> 10000 | J15: UGLL0BO9VY | K15: 6/19/2026/21/07/2026 | L15: JULY | M15: =H15-I15 -> -10035
A16: H8 | B16: BONIFACE | C16: 0703962575 | E16: 12100 | F16: 675 | G16: =JUNE!M16 -> 50 | H16: =D16+E16+G16+F16 -> 12825 | I16: 12224 | K16: 04.07.2026 | L16: JULY | M16: =H16-I16 -> 601 | O16: SIGNED
A17: H9 | B17: ROBERT | C17: 0726405930 | E17: 14100 | F17: 1710 | G17: =JUNE!M17 -> 0 | H17: =D17+E17+G17+F17 -> 15810 | I17: 14000 | J17: UGC13AU5VS | K17: 12/07/2-26 | L17: JULY | M17: =H17-I17 -> 1810
A18: H10 | B18: BEATRICE | C18: 0711729058 | E18: 10100 | F18: 495 | G18: =JUNE!M18 -> 460 | H18: =D18+E18+G18+F18 -> 11055 | I18: 10495 | J18: UG1RI9RL0D | K18: 46204 | L18: JULY | M18: =H18-I18 -> 560 | O18: SIGNED
A19: H11 | B19: PETER | C19: 0708568404 | E19: 10100 | F19: 60 | G19: =JUNE!M19 -> 105 | H19: =D19+E19+G19+F19 -> 10265 | I19: 10160 | J19: UG1K89S0O8 | K19: 46204 | L19: JULY | M19: =H19-I19 -> 105
A20: H12 | B20: GIDEON | C20: 0712026963 | E20: 10100 | F20: 285 | G20: =JUNE!M20 -> 0 | H20: =D20+E20+G20+F20 -> 10385 | I20: 10385 | J20: UG995APBSD | K20: 46212 | L20: JULY | M20: =H20-I20 -> 0 | O20: SIGNED
A21: H13 | B21: SHAWN RATEMO | C21: 0716484383/'0721832745 | E21: 10100 | F21: 285 | G21: =JUNE!M21 -> 400 | H21: =D21+E21+G21+F21 -> 10785 | I21: 10300 | J21: UGA7VB7V16 | K21: 46213 | L21: JULY | M21: =H21-I21 -> 485 | O21: SIGNED
A22: H14 | B22: MOMANYI KENNEDY | C22: 0114982450 | E22: 10100 | F22: 675 | G22: =JUNE!M22 -> -455 | H22: =D22+E22+G22+F22 -> 10320 | I22: 10100 | J22: UG4DIA64O7 | K22: 46207 | L22: JULY | M22: =H22-I22 -> 220 | O22: SIGNED
A23: H15 | B23: RONO ELIJAH | C23: 0745935239 | E23: 10100 | F23: 840 | G23: =JUNE!M23 -> 5225 | H23: =D23+E23+G23+F23 -> 16165 | I23: 22500 | J23: UFP1F97N0X | K23: 46198 | L23: JULY | M23: =H23-I23 -> -6335 | O23: SIGNED
A24: H16 | B24: KELVIN GITONGA | C24: 0792391382 | E24: 10100 | F24: 360 | G24: =JUNE!M24 -> -105 | H24: =D24+E24+G24+F24 -> 10355 | I24: 10460 | J24: UG7R49UD7O | K24: 46210 | L24: JULY | M24: =H24-I24 -> -105 | O24: SIGNED | P24: CR | Q24: =I57/H57*100 -> 125.25102
A25: S1 | B25: VIVIAN | C25: 0748596476 | E25: 10100 | F25: 330 | G25: =JUNE!M25 -> 669 | H25: =D25+E25+G25+F25 -> 11099 | I25: =10330 -> 10330 | J25: UG5KDA7TVQ | K25: 46208 | L25: JULY | M25: =H25-I25 -> 769 | O25: SIGNED
A26: S2 | B26: LINDA | C26: 0748689851 | E26: 10100 | F26: 120 | G26: =JUNE!M26 -> 0 | H26: =D26+E26+G26+F26 -> 10220 | I26: 10220 | J26: UG65VAFFWG | K26: 46209 | L26: JULY | M26: =H26-I26 -> 0 | O26: SIGNED
A27: S3 | B27: WARREN | C27: 0769883948 | E27: 10100 | F27: 435 | G27: =JUNE!M27 -> -680 | H27: =D27+E27+G27+F27 -> 9855 | I27: 10535 | J27: UG59RA75L2 | K27: 46208 | L27: JULY | M27: =H27-I27 -> -680 | O27: SIGNED
A28: S4 | B28: SCOLA | C28: 0793889379 | E28: 10100 | F28: 495 | G28: =JUNE!M28 -> -9305 | H28: =D28+E28+G28+F28 -> 1290 | I28: =10000 -> 10000 | J28: UGRHE0R2YO | K28: 46230 | L28: JULY | M28: =H28-I28 -> -8710 | P28: CR | Q28: 75.570748
A29: S5 | B29: CARETAKER | G29: =JUNE!M29 -> 0 | H29: =D29+E29+G29+F29 -> 0 | L29: JULY | M29: =H29-I29 -> 0
A30: S6 | B30: IMELDA | C30: 0723500330 | E30: 10100 | F30: 180 | G30: =JUNE!M30 -> 105 | H30: =D30+E30+G30+F30 -> 10385 | I30: =10300+10300 -> 20600 | J30: UGAD3ATQTA/ UGV2F1HN9L | K30: 7/10/2026 / 31.07.2026 | L30: JULY | M30: =H30-I30 -> -10215 | O30: SIGNED | P30: 2 BROKEN PADLOCK ADD 1000
A31: S7 | B31: EVANS | C31: 0702377661 | E31: 10100 | F31: 30 | G31: =JUNE!M31 -> -8 | H31: =D31+E31+G31+F31 -> 10122 | I31: =10130 -> 10130 | J31: UG5RPAGCZ1 | K31: 46149 | L31: JULY | M31: =H31-I31 -> -8
A32: S8 | B32: BRIAN CHERUIYOT | C32: 0746324500 | E32: 10100 | F32: 900 | G32: =JUNE!M32 -> 1385 | H32: =D32+E32+G32+F32 -> 12385 | I32: 10100 | J32: UGC7QBBRTE | K32: 46215 | L32: JULY | M32: =H32-I32 -> 2285 | O32: SIGNED
A33: S9 | B33: DORCAS KENANDA | C33: 0723433108 | E33: 10100 | F33: 105 | G33: =JUNE!M33 -> -155 | H33: =D33+E33+G33+F33 -> 10050 | I33: =10205 -> 10205 | J33: UG447ASGZV | K33: 46119 | L33: JULY | M33: =H33-I33 -> -155 | O33: SIGNED
A34: S10 | B34: MONICAH | C34: 0740454928 | E34: 10100 | F34: 120 | G34: =JUNE!M34 -> 110 | H34: =D34+E34+G34+F34 -> 10330 | I34: 10220 | J34: UGASG374MJ | K34: 46213 | L34: JULY | M34: =H34-I34 -> 110
A35: S11 | B35: IAN KAMAU | C35: 0745292688 | E35: 10100 | F35: 120 | G35: =JUNE!M35 -> -330 | H35: =D35+E35+G35+F35 -> 9890 | I35: 10220 | J35: UG4MSA2FBQ | K35: 46207 | L35: JULY | M35: =H35-I35 -> -330
A36: S12 | B36: JUSTINE | C36: 0724282631 | E36: 10100 | F36: 90 | G36: =JUNE!M36 -> -10295 | H36: =D36+E36+G36+F36 -> -105 | I36: =10090 -> 10090 | J36: S3OCZEBB1D6 | K36: 46088 | L36: JULY | M36: =H36-I36 -> -10195
A37: S13 | B37: DERRICK | C37: 0707280087 | E37: 10100 | F37: 225 | G37: =JUNE!M37 -> 35 | H37: =D37+E37+G37+F37 -> 10360 | I37: 10325 | J37: UG7IAAGD95 | K37: 46210 | L37: JULY | M37: =H37-I37 -> 35
A38: S14 | B38: VINCENT | C38: 0798467289 | E38: 10100 | F38: 180 | G38: =JUNE!M38 -> 435 | H38: =D38+E38+G38+F38 -> 10715 | I38: =10595 -> 10595 | J38: UFU199HIHJ | K38: 30/06/2026 | L38: JULY | M38: =H38-I38 -> 120
A39: S15 | B39: ARON | C39: 0706195266 | E39: 10100 | F39: 135 | G39: =JUNE!M39 -> 295 | H39: =D39+E39+G39+F39 -> 10530 | I39: 10135 | J39: UG75QB0539 | K39: 46210 | L39: JULY | M39: =H39-I39 -> 395 | O39: SIGNED
A40: S16 | B40: BEN SAKWA | C40: 0725451845 | E40: 10100 | F40: 720 | G40: =JUNE!M40 -> 1650 | H40: =D40+E40+G40+F40 -> 12470 | I40: =10100+10100+1170+1650 -> 23020 | J40: UFQ489RVM1/'UGQ481B48U/UGQ481B07T/UGQ481B497 | K40: 6/26/2026/26.07.2026 | L40: JULY | M40: =H40-I40 -> -10550 | O40: SIGNED
A41: S17 | B41: DENNIS OWINO | C41: 0712299080 | E41: 10100 | F41: 90 | G41: =JUNE!M41 -> 100 | H41: =D41+E41+G41+F41 -> 10290 | I41: =8000 -> 8000 | J41: UGQIE0XXD9 | K41: 26/07/2026 | L41: JULY | M41: =H41-I41 -> 2290 | N41: 24TH | O41: SIGNED
A42: S18 | B42: LIZZIE NYAMBURA | C42: 0792838695 | E42: 10100 | F42: 165 | G42: =JUNE!M42 -> 148 | H42: =D42+E42+G42+F42 -> 10413 | I42: 10162 | J42: UG16L9R6P2 | K42: 46204 | L42: JULY | M42: =H42-I42 -> 251 | O42: SIGNED
A43: S19 | B43: LINAH WAITHIRA NDERU | C43: 0786286496 | E43: 10100 | F43: 45 | G43: =JUNE!M43 -> 205 | H43: =D43+E43+G43+F43 -> 10350 | I43: 10145 | J43: UG91VATP1C | K43: 46212 | L43: JULY | M43: =H43-I43 -> 205 | O43: SIGNED
A44: S20 | B44: PHELISIA | C44: 0718117097 | E44: 10100 | F44: 345 | G44: =JUNE!M44 -> 584 | H44: =D44+E44+G44+F44 -> 11029 | I44: =4000+2000+3000 -> 9000 | J44: UG52TA5MJ5/UG42TA0U7J/ UGV2T14LO3 | K44: 7/8/2026/31.07.2026 | L44: JULY | M44: =H44-I44 -> 2029 | O44: SIGNED
A45: S21 | B45: JOEL MAINA | C45: 0797262139 | E45: 10100 | F45: 330 | G45: =JUNE!M45 -> -16430 | H45: =D45+E45+G45+F45 -> -6000 | I45: 10330 | J45: UG90TAWF2J | K45: 46212 | L45: JULY | M45: =H45-I45 -> -16330 | O45: SIGNED
A46: S22 | B46: JONA KIBET | C46: 0790405201 | E46: 10100 | F46: 585 | G46: =JUNE!M46 -> -111 | H46: =D46+E46+G46+F46 -> 10574 | I46: =10685 -> 10685 | J46: UG4QO9SELK | K46: 46119 | L46: JULY | M46: =H46-I46 -> -111 | O46: SIGNED
A47: S23 | B47: CINDY | C47: 0726239783 | E47: 10100 | F47: 30 | G47: =JUNE!M47 -> 90 | H47: =D47+E47+G47+F47 -> 10220 | I47: =10130 -> 10130 | J47: UG5LXA0W9G | K47: 46149 | L47: JULY | M47: =H47-I47 -> 90
A48: S24 | B48: YASHON | C48: 0711167127 | E48: 10100 | F48: 90 | G48: =JUNE!M48 -> 100 | H48: =D48+E48+G48+F48 -> 10290 | I48: 10190 | J48: UG6I9A7R4J | K48: 46209 | L48: JULY | M48: =H48-I48 -> 100 | O48: SIGNED
A49: S25 | B49: LIZZIE | C49: 0706359132 | E49: 10100 | F49: 150 | G49: =JUNE!M49 -> 175 | H49: =D49+E49+G49+F49 -> 10425 | I49: =10250 -> 10250 | J49: UG5U91LAK5 | K49: 46149 | L49: JULY | M49: =H49-I49 -> 175
A50: S26 | B50: LUCY | C50: 0703357741 | E50: 10100 | F50: 90 | G50: =JUNE!M50 -> -10 | H50: =D50+E50+G50+F50 -> 10180 | I50: 10190 | J50: UG885ARKSI | K50: 46211 | L50: JULY | M50: =H50-I50 -> -10
A51: S27 | B51: DOROTHY | C51: 0793749115 | E51: 10100 | F51: 180 | G51: =JUNE!M51 -> -40 | H51: =D51+E51+G51+F51 -> 10240 | I51: =10280+10460 -> 20740 | J51: UG3B1A7NIY/UGVB11DHTK | K51: 3/7/2026/31.07.2026 | L51: JULY | M51: =H51-I51 -> -10500 | O51: SIGNED
A52: S28 | B52: STELLA | C52: 0745586458 | E52: 10100 | F52: 30 | G52: =JUNE!M52 -> 30 | H52: =D52+E52+G52+F52 -> 10160 | I52: =20100+10560+15500 -> 46160 | J52: UFSIZ905LG/ UGVDS1H73X/ UGJDX1H72X | K52: 6/29/2026/31.07.2026/17.07.2026 | L52: JULY | M52: =H52-I52 -> -36000
A53: S29 | B53: JUMA | C53: 0702146655 | E53: 10100 | F53: 390 | G53: =JUNE!M53 -> 445 | H53: =D53+E53+G53+F53 -> 10935 | I53: =10490+10655 -> 21145 | J53: UG1A2A361F/UGUA21GNDU | K53: 7/1/2026/ 30/07/2026 | L53: JULY | M53: =H53-I53 -> -10210
A54: S30 | B54: JOSEPH MUGO | C54: 0704339161 | E54: 10100 | F54: 195 | G54: =JUNE!M54 -> -80 | H54: =D54+E54+G54+F54 -> 10215 | I54: =10295 -> 10295 | J54: UG5SB1Y7LZ | K54: 05.07.2026 | L54: JULY | M54: =H54-I54 -> -80 | O54: SIGNED
A55: S31 | B55: TIMOTHY KURIA | C55: 0797778633 | E55: 10100 | F55: 90 | G55: =JUNE!M55 -> 100 | H55: =D55+E55+G55+F55 -> 10290 | I55: =10190 -> 10190 | J55: UG46C9MF36 | K55: 46119 | L55: JULY | M55: =H55-I55 -> 100 | O55: SIGNED
A56: S32 | B56: MRENJE CHRISANTHUS | C56: 0794033100 | E56: 10100 | F56: 210 | G56: =JUNE!M56 -> 340 | H56: =D56+E56+G56+F56 -> 10650 | I56: =10000+210 -> 10210 | J56: UG3BLAGQQM/UG2BLA9I9I | K56: 46205 | L56: JULY | M56: =H56-I56 -> 440 | O56: SIGNED
A57: Totals | E57: =SUM(E9:E56) -> 480700 | F57: =SUM(F9:F56) -> 14655 | G57: =SUM(G9:G56) -> -30348 | H57: =SUM(H9:H56) -> 465007 | I57: =SUM(I9:I56) -> 582426 | M57: =SUM(M9:M56) -> -117419
A59: Deductions
A60: Less Management fees | I60: =6%*I57 -> 34945.56
A61: TOTAL DEDUCTIONS | I61: =SUM(I60:I60) -> 34945.56
A63: BAL B/F | I63: =JUNE!M64 -> 29273.1 | J63: Paid | L63: Paid | M63: Balance
A64: AMOUNT DUE | I64: =I61 -> 34945.56 | M64: =I64-J64-L64 -> 34945.56
A66: AUTHORISED BY JOSEPH GITHINJI | M66: 46234
E70: =I57/H57*100 -> 125.25102

Sheet AUGUST
C1: LOBBY ENTERPRISES
A2: PROPERTY MANAGERS AND ESTATE AGENTS
A3: AUGUST 2026
J4: P.O.BOX 11987
A5: STUDIO HAVEN | J5: TEL : 0722711933/4454322
A6: A/C | I6: Care taker | J6: ELIZABETH
I7: Phone no | J7: 0796292019
A8: HSE NO | B8: NAME | C8: PHONE NO | D8: DEPOSIT PAID | E8: MONTHLY RENT | F8: WATER BILL | G8: BAL B/D | H8: RENT DUE | I8: RENT PAID | J8: RCT NO | K8: DATE | L8: PERIOD | M8: BALANCE | N8: STATUS | O8: FORMS
A9: H1 | B9: ROSE | C9: 0707714065 | E9: 10100 | F9: 525 | G9: =JULY!M9 -> 0 | H9: =D9+E9+G9+F9 -> 10625 | I9: =10625 -> 10625 | J9: UH3HM1D4NO | K9: 03.08.2026 | L9: AUGUST | M9: =H9-I9 -> 0
A10: H2 | B10: BENSON | C10: 0741776284 | E10: 10100 | F10: 600 | G10: =JULY!M10 -> 55 | H10: =D10+E10+G10+F10 -> 10755 | I10: =10700 -> 10700 | J10: UHBAY28RPS | K10: 11.08.2026 | L10: AUGUST | M10: =H10-I10 -> 55 | O10: SIGNED
A11: H3 | B11: TESSA MARRIE | C11: 0716507709 | E11: 10100 | F11: 315 | G11: =JULY!M11 -> 1095 | H11: =D11+E11+G11+F11 -> 11510 | I11: 9500 | J11: UH8OV2JRN8 | K11: 8TH AUGUST | L11: AUGUST | M11: =H11-I11 -> 2010
A12: H4 | B12: JOY | C12: 0724674470 | E12: 10100 | F12: 255 | G12: =JULY!M12 -> -4645 | H12: =D12+E12+G12+F12 -> 5710 | I12: =10355 -> 10355 | J12: UH8OH1WPAA | K12: 08.08.2026 | L12: AUGUST | M12: =H12-I12 -> -4645 | O12: SIGNED
A13: H5 | B13: PAUL | C13: 0723316248/0769953112 | E13: 10100 | F13: 975 | G13: =JULY!M13 -> 12960 | H13: =D13+E13+G13+F13 -> 24035 | I13: =10000 -> 10000 | J13: UH5OF1XFUM | K13: 05.08.2026 | L13: AUGUST | M13: =H13-I13 -> 14035 | N13: LOCKED | O13: SIGNED
A14: H6 | B14: MARY MESUSWA | C14: 0757079026 | E14: 10100 | F14: 480 | G14: =JULY!M14 -> -9500 | H14: =D14+E14+G14+F14 -> 1080 | L14: AUGUST | M14: =H14-I14 -> 1080
A15: H7 | B15: MUNYIRI WACHIRA | C15: 0700935843 | E15: 10100 | F15: 45 | G15: =JULY!M15 -> -10035 | H15: =D15+E15+G15+F15 -> 110 | L15: AUGUST | M15: =H15-I15 -> 110
A16: H8 | B16: BONIFACE | C16: 0703962575 | E16: 12100 | F16: 1110 | G16: =JULY!M16 -> 601 | H16: =D16+E16+G16+F16 -> 13811 | I16: =13210 -> 13210 | K16: 06.08.2026 | L16: AUGUST | M16: =H16-I16 -> 601 | O16: SIGNED
A17: H9 | B17: ROBERT | C17: 0726405930 | E17: 14100 | F17: 1395 | G17: =JULY!M17 -> 1810 | H17: =D17+E17+G17+F17 -> 17305 | I17: =14000 -> 14000 | J17: UHB132AW8F | K17: 46245 | L17: AUGUST | M17: =H17-I17 -> 3305
A18: H10 | B18: BEATRICE | C18: 0711729058 | E18: 10100 | F18: 720 | G18: =JULY!M18 -> 560 | H18: =D18+E18+G18+F18 -> 11380 | I18: =10720 -> 10720 | J18: UH3RI1L2CG | K18: 03.08.2026 | L18: AUGUST | M18: =H18-I18 -> 660 | O18: SIGNED
A19: H11 | B19: PETER | C19: 0708568404 | E19: 10100 | F19: 180 | G19: =JULY!M19 -> 105 | H19: =D19+E19+G19+F19 -> 10385 | I19: =10280 -> 10280 | J19: UH5K81TP8D | K19: 05.08.2026 | L19: AUGUST | M19: =H19-I19 -> 105
A20: H12 | B20: DUNCAN CHERUIYOT | C20: 0708748835 | D20: 10000 | E20: 10100 | F20: 135 | G20: 0 | H20: =D20+E20+G20+F20 -> 20235 | I20: 15000 | J20: UH5H61UK5KV | K20: 05.08.2026 | L20: AUGUST | M20: =H20-I20 -> 5235 | O20: SIGNED
A21: H13 | B21: SHAWN RATEMO | C21: 0716484383/'0721832745 | E21: 10100 | F21: 300 | G21: =JULY!M21 -> 485 | H21: =D21+E21+G21+F21 -> 10885 | I21: 10500 | J21: UHD7V35X1T | K21: 13TH AUGUST | L21: AUGUST | M21: =H21-I21 -> 385 | O21: SIGNED
A22: H14 | B22: MOMANYI KENNEDY | C22: 0114982450 | E22: 10100 | F22: 690 | G22: =JULY!M22 -> 220 | H22: =D22+E22+G22+F22 -> 11010 | I22: =10100+10355 -> 20455 | J22: UH5591IKKV / UH8OH1WPAA | K22: 05.08.2026/ 8/8/2026 | L22: AUGUST | M22: =H22-I22 -> -9445 | O22: SIGNED
A23: H15 | B23: RONO ELIJAH | C23: 0745935239 | E23: 10100 | F23: 1050 | G23: =JULY!M23 -> -6335 | H23: =D23+E23+G23+F23 -> 4815 | I23: =15800 -> 15800 | J23: UHS1F4MR4Y | K23: 46262 | L23: AUGUST | M23: =H23-I23 -> -10985 | O23: SIGNED
A24: H16 | B24: KELVIN GITONGA | C24: 0792391382 | E24: 10100 | F24: 555 | G24: =JULY!M24 -> -105 | H24: =D24+E24+G24+F24 -> 10550 | I24: =10655 -> 10655 | J24: UH6R41CF6K | K24: 06.08.2026 | L24: AUGUST | M24: =H24-I24 -> -105 | O24: SIGNED
A25: S1 | B25: VIVIAN | C25: 0748596476 | E25: 10100 | F25: 525 | G25: =JULY!M25 -> 769 | H25: =D25+E25+G25+F25 -> 11394 | I25: =10525 -> 10525 | J25: UH5KD1T9K3 | K25: 05.08.2026 | L25: AUGUST | M25: =H25-I25 -> 869 | O25: SIGNED
A26: S2 | B26: LINDA | C26: 0748689851 | E26: 10100 | F26: 150 | G26: =JULY!M26 -> 0 | H26: =D26+E26+G26+F26 -> 10250 | I26: =10250 -> 10250 | J26: UH65V1YCZQ | K26: 06.08.2026 | L26: AUGUST | M26: =H26-I26 -> 0 | O26: SIGNED
A27: S3 | B27: WARREN | C27: 0769883948 | E27: 10100 | F27: 645 | G27: =JULY!M27 -> -680 | H27: =D27+E27+G27+F27 -> 10065 | I27: =10745 -> 10745 | J27: UH39R1M570 | K27: 03.08.2026 | L27: AUGUST | M27: =H27-I27 -> -680 | O27: SIGNED
A28: S4 | B28: SCOLA | C28: 0793889379 | E28: 10100 | F28: 540 | G28: =JULY!M28 -> -8710 | H28: =D28+E28+G28+F28 -> 1930 | L28: AUGUST | M28: =H28-I28 -> 1930
A29: S5 | B29: CARETAKER | F29: 0 | G29: =JULY!M29 -> 0 | H29: =D29+E29+G29+F29 -> 0 | L29: AUGUST | M29: =H29-I29 -> 0
A30: S6 | B30: IMELDA | C30: 0723500330 | E30: 10100 | F30: 270 | G30: =JULY!M30 -> -10215 | H30: =D30+E30+G30+F30 -> 155 | L30: AUGUST | M30: =H30-I30 -> 155 | O30: SIGNED
A31: S7 | B31: EVANS | C31: 0702377661 | E31: 10100 | F31: 30 | G31: =JULY!M31 -> -8 | H31: =D31+E31+G31+F31 -> 10122 | I31: =10130 -> 10130 | J31: UH6CP1VL4K | K31: 06.08.2026 | L31: AUGUST | M31: =H31-I31 -> -8
A32: S8 | B32: BRIAN CHERUIYOT | C32: 0746324500 | E32: 10100 | F32: 1155 | G32: =JULY!M32 -> 2285 | H32: =D32+E32+G32+F32 -> 13540 | I32: =10000 -> 10000 | J32: UHM7Q43FUN | K32: 46256 | L32: AUGUST | M32: =H32-I32 -> 3540 | O32: SIGNED
A33: S9 | B33: DORCAS KENANDA | C33: 0723433108 | E33: 10100 | F33: 270 | G33: =JULY!M33 -> -155 | H33: =D33+E33+G33+F33 -> 10215 | I33: =10370 -> 10370 | J33: UHS475C51Q | K33: 46262 | L33: AUGUST | M33: =H33-I33 -> -155 | O33: SIGNED
A34: S10 | B34: MONICAH | C34: 0740454928 | E34: 10100 | F34: 195 | G34: =JULY!M34 -> 110 | H34: =D34+E34+G34+F34 -> 10405 | I34: =10720+10295 -> 21015 | J34: UH3RI1L2CG/UHASG4UJOP | K34: 03.08.2026/ 10.08.2026 | L34: AUGUST | M34: =H34-I34 -> -10610
A35: S11 | B35: IAN KAMAU | C35: 0745292688 | E35: 10100 | F35: 105 | G35: =JULY!M35 -> -330 | H35: =D35+E35+G35+F35 -> 9875 | I35: =10205 -> 10205 | J35: UH6MS1XYHO | K35: 06.08.2026 | L35: AUGUST | M35: =H35-I35 -> -330
A36: S12 | B36: JUSTINE | C36: 0724282631 | E36: 10100 | F36: 150 | G36: =JULY!M36 -> -10195 | H36: =D36+E36+G36+F36 -> 55 | I36: =10150 -> 10150 | J36: B3QFG936YO2 | K36: 25.08.2026 | L36: AUGUST | M36: =H36-I36 -> -10095
A37: S13 | B37: DERRICK | C37: 0707280087 | E37: 10100 | F37: 195 | G37: =JULY!M37 -> 35 | H37: =D37+E37+G37+F37 -> 10330 | I37: =10295 -> 10295 | J37: UH5IA1SDNQ | K37: 05.08.2026 | L37: AUGUST | M37: =H37-I37 -> 35
A38: S14 | B38: VINCENT | C38: 0724680684 | E38: 10100 | F38: 300 | G38: =JULY!M38 -> 120 | H38: =D38+E38+G38+F38 -> 10520 | I38: 10400 | J38: UH11917NP2 | K38: 1ST AUGUST | L38: AUGUST | M38: =H38-I38 -> 120
A39: S15 | B39: FRANCIS LOKITA | C39: 0706142428 | D39: 10000 | E39: 10100 | H39: =D39+E39+G39+F39 -> 20100 | I39: 20100 | J39: UH76Q1T9QB | K39: 7TH AUGUST | L39: AUGUST | M39: =H39-I39 -> 0 | O39: SIGNED
A40: S16 | B40: BEN SAKWA | C40: 0725451845 | E40: 10100 | F40: 750 | G40: =JULY!M40 -> -10550 | H40: =D40+E40+G40+F40 -> 300 | I40: =750+10100 -> 10850 | J40: UHF483PFP1 /UHP484VBGG | K40: 8/15/2026/ 8/25/2026 | L40: AUGUST | M40: =H40-I40 -> -10550 | O40: SIGNED
A41: S17 | B41: DENNIS OWINO | C41: 0712299080 | E41: 10100 | F41: 90 | G41: =JULY!M41 -> 2290 | H41: =D41+E41+G41+F41 -> 12480 | I41: =6000 -> 6000 | J41: UHT4A5IT17 | K41: 29.08.2026 | L41: AUGUST | M41: =H41-I41 -> 6480 | N41: LOCKED | O41: SIGNED
A42: S18 | B42: LIZZIE NYAMBURA | C42: 0792838695 | E42: 10100 | F42: 240 | G42: =JULY!M42 -> 251 | H42: =D42+E42+G42+F42 -> 10591 | I42: =10240 -> 10240 | J42: UH16L19GK1 | K42: 01.08.2026 | L42: AUGUST | M42: =H42-I42 -> 351 | O42: SIGNED
A43: S19 | B43: JOSEPH NDUNG'U | C43: 0725823244 | D43: 10000 | E43: 10100 | F43: 0 | G43: 0 | H43: =D43+E43+G43+F43 -> 20100 | I43: =20100 -> 20100 | J43: UH2M51MVUP | K43: 02.08.2026 | L43: AUGUST | M43: =H43-I43 -> 0 | O43: SIGNED
A44: S20 | B44: PHELISIA | C44: 0718117097 | E44: 10100 | F44: 600 | G44: =JULY!M44 -> 2029 | H44: =D44+E44+G44+F44 -> 12729 | I44: =2000+9000 -> 11000 | J44: UH12T1ANVH/UHI2T35MPT | K44: 01.08.2026/18TH.08.2026 | L44: AUGUST | M44: =H44-I44 -> 1729 | O44: SIGNED
A45: S21 | B45: JOEL MAINA | C45: 0797262139 | E45: 10100 | F45: 465 | G45: =JULY!M45 -> -16330 | H45: =D45+E45+G45+F45 -> -5765 | I45: =10465 -> 10465 | J45: UH90T2KI4F | K45: 09.08.2026 | L45: AUGUST | M45: =H45-I45 -> -16230 | O45: SIGNED
A46: S22 | B46: JONA KIBET | C46: 0790405201 | E46: 10100 | F46: 885 | G46: =JULY!M46 -> -111 | H46: =D46+E46+G46+F46 -> 10874 | I46: =10985 -> 10985 | J46: UH3QO19DX4 | K46: 03.08.2026 | L46: AUGUST | M46: =H46-I46 -> -111 | O46: SIGNED
A47: S23 | B47: CINDY | C47: 0726239783 | E47: 10100 | F47: 330 | G47: =JULY!M47 -> 90 | H47: =D47+E47+G47+F47 -> 10520 | I47: =10430 -> 10430 | J47: UH3LX1BJGF | K47: 03.08.2026 | L47: AUGUST | M47: =H47-I47 -> 90
A48: S24 | B48: YASHON | C48: 0711167127 | E48: 10100 | F48: 120 | G48: =JULY!M48 -> 100 | H48: =D48+E48+G48+F48 -> 10320 | I48: =10220 -> 10220 | J48: UH7I91VHXQ | K48: 07.08.2026 | L48: AUGUST | M48: =H48-I48 -> 100 | O48: SIGNED
A49: S25 | B49: LIZZIE | C49: 0706359132 | E49: 10100 | F49: 345 | G49: =JULY!M49 -> 175 | H49: =D49+E49+G49+F49 -> 10620 | I49: =10445 -> 10445 | J49: UH5U933AA3 | K49: 05.08.2026 | L49: AUGUST | M49: =H49-I49 -> 175
A50: S26 | B50: LUCY | C50: 0703357741 | E50: 10100 | F50: 210 | G50: =JULY!M50 -> -10 | H50: =D50+E50+G50+F50 -> 10300 | I50: =10310 -> 10310 | J50: UH8852DRS8 | K50: 46242 | L50: AUGUST | M50: =H50-I50 -> -10
A51: S27 | B51: DOROTHY | C51: 0793749115 | E51: 10100 | F51: 360 | G51: =JULY!M51 -> -10500 | H51: =D51+E51+G51+F51 -> -40 | L51: AUGUST | M51: =H51-I51 -> -40 | O51: SIGNED
A52: S28 | B52: STELLA | C52: 0745586458 | E52: 10100 | F52: 345 | G52: =JULY!M52 -> -36000 | H52: =D52+E52+G52+F52 -> -25555 | L52: AUGUST | M52: =H52-I52 -> -25555
A53: S29 | B53: JUMA | C53: 0702146655 | E53: 10100 | F53: 555 | G53: =JULY!M53 -> -10210 | H53: =D53+E53+G53+F53 -> 445 | L53: AUGUST | M53: =H53-I53 -> 445
A54: S30 | B54: JOSEPH MUGO | C54: 0704339161 | E54: 10100 | F54: 375 | G54: =JULY!M54 -> -80 | H54: =D54+E54+G54+F54 -> 10395 | I54: =10475 -> 10475 | J54: UH5SB3HGEF | K54: 05.08.2026 | L54: AUGUST | M54: =H54-I54 -> -80 | O54: SIGNED
A55: S31 | B55: TIMOTHY KURIA | C55: 0797778633 | E55: 10100 | F55: 150 | G55: =JULY!M55 -> 100 | H55: =D55+E55+G55+F55 -> 10350 | I55: =10250 -> 10250 | J55: UH16C0QK4J | K55: 01.08.2026 | L55: AUGUST | M55: =H55-I55 -> 100 | O55: SIGNED
A56: S32 | B56: MRENJE CHRISANTHUS | C56: 0794033100 | E56: 10100 | F56: 315 | G56: =JULY!M56 -> 440 | H56: =D56+E56+G56+F56 -> 10855 | I56: =10315 -> 10315 | J56: UH2BL1VRQ6 | K56: 02.08.2026 | L56: AUGUST | M56: =H56-I56 -> 540 | O56: SIGNED
A57: Totals | E57: =SUM(E9:E56) -> 480700 | F57: =SUM(F9:F56) -> 19995 | G57: =SUM(G9:G56) -> -118019 | H57: =SUM(H9:H56) -> 412676 | I57: =SUM(I9:I56) -> 468070 | M57: =SUM(M9:M56) -> -55394
A59: Deductions
A60: Less Management fees | I60: =6%*I57 -> 28084.2
A61: TOTAL DEDUCTIONS | I61: =SUM(I60:I60) -> 28084.2
A63: BAL B/F | I63: =JUNE!M64 -> 29273.1 | J63: Paid | L63: Paid | M63: Balance
A64: AMOUNT DUE | I64: =I61 -> 28084.2 | M64: =I64-J64-L64 -> 28084.2
A66: AUTHORISED BY JOSEPH GITHINJI | M66: 46265
E70: =I57/H57*100 -> 113.42312

Sheet SEPTEMBER
C1: LOBBY ENTERPRISES
A2: PROPERTY MANAGERS AND ESTATE AGENTS
A3: JULY 2026
J4: P.O.BOX 11987
A5: STUDIO HAVEN | J5: TEL : 0722711933/4454322
A6: A/C | I6: Care taker | J6: ELIZABETH
I7: Phone no | J7: 0796292019
A8: HSE NO | B8: NAME | C8: PHONE NO | D8: DEPOSIT PAID | E8: MONTHLY RENT | F8: WATER BILL | G8: BAL B/D | H8: RENT DUE | I8: RENT PAID | J8: RCT NO | K8: DATE | L8: PERIOD | M8: BALANCE | N8: FORMS | O8: STATUS
A9: H1 | B9: ROSE | C9: 0707714065 | E9: 10100 | F9: 570 | G9: =AUGUST!M9 -> 0 | H9: =D9+E9+G9+F9 -> 10670 | I9: =10670 -> 10670 | J9: UI3HM50EK2 | K9: 46268 | L9: SEPTEMBER | M9: =H9-I9 -> 0 | N9: SIGNED
A10: H2 | B10: BENSON | C10: 0741776284 | E10: 10100 | F10: 390 | G10: =AUGUST!M10 -> 55 | H10: =D10+E10+G10+F10 -> 10545 | I10: =10500 -> 10500 | J10: UI9AY5LSS2 | K10: 46274 | L10: SEPTEMBER | M10: =H10-I10 -> 45 | N10: SIGNED
A11: H3 | B11: TESSA MARRIE | C11: 0716507709 | E11: 10100 | F11: 180 | G11: =AUGUST!M11 -> 2010 | H11: =D11+E11+G11+F11 -> 12290 | I11: =4500+7790 -> 12290 | J11: UI8OV65347 / UIAAJ5TNLY | K11: 9/8/2026 / 9/10/2026 | L11: SEPTEMBER | M11: =H11-I11 -> 0 | N11: SIGNED
A12: H4 | B12: JOY | C12: 0724674470 | E12: 10100 | F12: 255 | G12: =AUGUST!M12 -> -4645 | H12: =D12+E12+G12+F12 -> 5710 | I12: =10255 -> 10255 | J12: UIAOH5RL8Q | K12: 9/10/2026 | L12: SEPTEMBER | M12: =H12-I12 -> -4545 | N12: SIGNED
A13: H5 | B13: PAUL | C13: 0723316248 | E13: 10100 | F13: 375 | G13: =AUGUST!M13 -> 14035 | H13: =D13+E13+G13+F13 -> 24510 | I13: =22000 -> 22000 | J13: UI1OF50505OV | K13: 9/01/2026 | L13: SEPTEMBER | M13: =H13-I13 -> 2510 | N13: SIGNED | O13: Not responding
A14: H6 | B14: MARY MESUSWA | C14: 0757079026 | E14: 10100 | F14: 300 | G14: =AUGUST!M14 -> 1080 | H14: =D14+E14+G14+F14 -> 11480 | I14: =10300 -> 10300 | J14: UI1PY4NE9T | K14: 46266 | L14: SEPTEMBER | M14: =H14-I14 -> 1180 | N14: SIGNED | O14: Sent Payment breakdown
A15: H7 | B15: MUNYIRI WACHIRA | C15: 0700935843 | E15: 10100 | F15: 165 | G15: =AUGUST!M15 -> 110 | H15: =D15+E15+G15+F15 -> 10375 | I15: =10000 -> 10000 | J15: UHML03B7OU | K15: 8/22/2026 | L15: SEPTEMBER | M15: =H15-I15 -> 375 | N15: SIGNED | O15: To clear utility fee tmrw
A16: H8 | B16: BONIFACE | C16: 0703962575 | E16: 12100 | F16: 750 | G16: =AUGUST!M16 -> 601 | H16: =D16+E16+G16+F16 -> 13451 | I16: 12850 | J16: UI42M5NE86 | K16: 9/4/2026 | L16: SEPTEMBER | M16: =H16-I16 -> 601 | N16: SIGNED | O16: Not reachable
A17: H9 | B17: ROBERT | C17: 0726405930 | E17: 14100 | F17: 1110 | G17: =AUGUST!M17 -> 3305 | H17: =D17+E17+G17+F17 -> 18515 | I17: =14000 -> 14000 | J17: UIC1361SK3 | K17: 9/12/2026 | L17: SEPTEMBER | M17: =H17-I17 -> 4515 | N17: SIGNED | O17: Rude-declined the call
A18: H10 | B18: BEATRICE | C18: 0711729058 | E18: 10100 | F18: 765 | G18: =AUGUST!M18 -> 660 | H18: =D18+E18+G18+F18 -> 11525 | I18: =10765 -> 10765 | J18: UI4RI5C4ZM | K18: 46269 | L18: SEPTEMBER | M18: =H18-I18 -> 760 | N18: SIGNED
A19: H11 | B19: PETER | C19: 0708568404 | E19: 10100 | F19: 120 | G19: =AUGUST!M19 -> 105 | H19: =D19+E19+G19+F19 -> 10325 | I19: =10220 -> 10220 | J19: UI1K84X74N | K19: 46266 | L19: SEPTEMBER | M19: =H19-I19 -> 105 | N19: SIGNED
A20: H12 | B20: DUNCAN CHERUIYOT | C20: 0708748835 | E20: 10100 | F20: 135 | G20: =AUGUST!M20 -> 5235 | H20: =D20+E20+G20+F20 -> 15470 | I20: =10100 -> 10100 | J20: UIAOI6M196 | K20: 9/10/2026 | L20: SEPTEMBER | M20: =H20-I20 -> 5370 | N20: SIGNED | O20: Not responding
A21: H13 | B21: SHAWN RATEMO | C21: 0716484383/'0721832745 | E21: 10100 | F21: 420 | G21: =AUGUST!M21 -> 385 | H21: =D21+E21+G21+F21 -> 10905 | I21: =10500 -> 10500 | J21: UI37V5MSAS | K21: 46268 | L21: SEPTEMBER | M21: =H21-I21 -> 405 | N21: SIGNED
A22: H14 | B22: MOMANYI KENNEDY | C22: 0114982450 | E22: 10100 | F22: 900 | G22: =AUGUST!M22 -> -9445 | H22: =D22+E22+G22+F22 -> 1555 | I22: =11000 -> 11000 | J22: UI55952R3B | K22: 46270 | L22: SEPTEMBER | M22: =H22-I22 -> -9445 | N22: SIGNED
A23: H15 | B23: RONO ELIJAH | C23: 0745935239 | E23: 10100 | F23: 780 | G23: =AUGUST!M23 -> -10985 | H23: =D23+E23+G23+F23 -> -105 | L23: SEPTEMBER | M23: =H23-I23 -> -105 | N23: SIGNED | O23: 25th sep
A24: H16 | B24: KELVIN GITONGA | C24: 0792391382 | E24: 10100 | F24: 555 | G24: =AUGUST!M24 -> -105 | H24: =D24+E24+G24+F24 -> 10550 | I24: =10655 -> 10655 | J24: UI5R44SF2A | K24: 46270 | L24: SEPTEMBER | M24: =H24-I24 -> -105 | N24: SIGNED
A25: S1 | B25: VIVIAN | C25: 0748596476 | E25: 10100 | F25: 495 | G25: =AUGUST!M25 -> 869 | H25: =D25+E25+G25+F25 -> 11464 | I25: =10495 -> 10495 | J25: UI6KD5HQEV | K25: 46271 | L25: SEPTEMBER | M25: =H25-I25 -> 969 | N25: SIGNED | O25: To send msg
A26: S2 | B26: LINDA | C26: 0748689851 | E26: 10100 | F26: 150 | G26: =AUGUST!M26 -> 0 | H26: =D26+E26+G26+F26 -> 10250 | I26: =10250 -> 10250 | J26: UI55V5DG2U | K26: 46272 | L26: SEPTEMBER | M26: =H26-I26 -> 0 | N26: SIGNED
A27: S3 | B27: WARREN | C27: 0769883948 | E27: 10100 | F27: 510 | G27: =AUGUST!M27 -> -680 | H27: =D27+E27+G27+F27 -> 9930 | I27: =10610 -> 10610 | J27: UI69R55H9QF | K27: 46271 | L27: SEPTEMBER | M27: =H27-I27 -> -680 | N27: SIGNED
A28: S4 | B28: SCOLA | C28: 0793889379 | E28: 10100 | F28: 630 | G28: =AUGUST!M28 -> 1930 | H28: =D28+E28+G28+F28 -> 12660 | I28: =10530 -> 10530 | J28: UHTHE4JR76 | K28: 8/29/2026 | L28: SEPTEMBER | M28: =H28-I28 -> 2130 | N28: SIGNED | O28: 24TH
A29: S5 | B29: CARETAKER | F29: 0 | G29: =AUGUST!M29 -> 0 | H29: =D29+E29+G29+F29 -> 0 | L29: SEPTEMBER | M29: =H29-I29 -> 0 | N29: SIGNED
A30: S6 | B30: IMELDA | C30: 0723500330 | E30: 10100 | F30: 255 | G30: =AUGUST!M30 -> 155 | H30: =D30+E30+G30+F30 -> 10510 | I30: =10300 -> 10300 | J30: UI62F5TJYC | K30: 46271 | L30: SEPTEMBER | M30: =H30-I30 -> 210 | N30: SIGNED
A31: S7 | B31: EVANS | C31: 0702377661 | E31: 10100 | F31: 30 | G31: =AUGUST!M31 -> -8 | H31: =D31+E31+G31+F31 -> 10122 | I31: =10100 -> 10100 | J31: UI6CP5GTYO | K31: 9/6/2026 | L31: SEPTEMBER | M31: =H31-I31 -> 22 | N31: SIGNED
A32: S8 | B32: BRIAN CHERUIYOT | C32: 0746324500 | E32: 10100 | F32: 1110 | G32: =AUGUST!M32 -> 3540 | H32: =D32+E32+G32+F32 -> 14750 | I32: =10610 -> 10610 | J32: UIE7Q6TC9R | K32: \9/14/2026 | L32: SEPTEMBER | M32: =H32-I32 -> 4140 | N32: SIGNED
A33: S9 | B33: DORCAS KENANDA | C33: 0723433108 | E33: 10100 | F33: 195 | G33: =AUGUST!M33 -> -155 | H33: =D33+E33+G33+F33 -> 10140 | I33: =10295 -> 10295 | J33: UI347608T7 | K33: 46268 | L33: SEPTEMBER | M33: =H33-I33 -> -155 | N33: SIGNED
A34: S10 | B34: MONICAH | C34: 0740454928 | E34: 10100 | F34: 180 | G34: =AUGUST!M34 -> -10610 | H34: =D34+E34+G34+F34 -> -330 | I34: =10280 -> 10280 | J34: UI2LR4EJM1 | K34: 46267 | L34: SEPTEMBER | M34: =H34-I34 -> -10610 | N34: SIGNED
A35: S11 | B35: IAN KAMAU | C35: 0745292688 | E35: 10100 | F35: 135 | G35: =AUGUST!M35 -> -330 | H35: =D35+E35+G35+F35 -> 9905 | I35: =10235 -> 10235 | J35: UI5MS5DNX8 | K35: 46270 | L35: SEPTEMBER | M35: =H35-I35 -> -330 | N35: SIGNED
A36: S12 | B36: JUSTINE | C36: 0724282631 | E36: 10100 | F36: 45 | G36: =AUGUST!M36 -> -10095 | H36: =D36+E36+G36+F36 -> 50 | L36: SEPTEMBER | M36: =H36-I36 -> 50 | N36: SIGNED
A37: S13 | B37: DERRICK | C37: 0707280087 | E37: 10100 | F37: 255 | G37: =AUGUST!M37 -> 35 | H37: =D37+E37+G37+F37 -> 10390 | I37: =10355 -> 10355 | J37: UI6IA5I09Z | K37: 46271 | L37: SEPTEMBER | M37: =H37-I37 -> 35 | N37: SIGNED
A38: S14 | B38: VINCENT | C38: 0798467289 | E38: 10100 | F38: 300 | G38: =AUGUST!M38 -> 120 | H38: =D38+E38+G38+F38 -> 10520 | I38: =10400 -> 10400 | J38: UI2194W58B | K38: 9/2/2026 | L38: SEPTEMBER | M38: =H38-I38 -> 120 | N38: SIGNED
A39: S15 | B39: FRANCIS LOKITA | C39: 0706195266 | E39: 10100 | F39: 180 | G39: =AUGUST!M39 -> 0 | H39: =D39+E39+G39+F39 -> 10280 | I39: =10280 -> 10280 | J39: UI56Q56PND | K39: 46270 | L39: SEPTEMBER | M39: =H39-I39 -> 0 | N39: SIGNED
A40: S16 | B40: BEN SAKWA | C40: 0725451845 | E40: 10100 | F40: 195 | G40: =AUGUST!M40 -> -10550 | H40: =D40+E40+G40+F40 -> -255 | I40: =10100+195 -> 10295 | J40: UIO488IK1U / UIO488IOG7 | K40: 9/24/2026 | L40: SEPTEMBER | M40: =H40-I40 -> -10550 | N40: SIGNED
A41: S17 | B41: DENNIS OWINO | C41: 0712299080 | E41: 10100 | F41: 15 | G41: =AUGUST!M41 -> 6480 | H41: =D41+E41+G41+F41 -> 16595 | I41: =4000+5000+1000+2000 -> 12000 | J41: UI14A5VYD6 / UI14A5YH5Z / UI34A63Q07 /UIA4A6XSZO | K41: 9/1/2026/ 9/1/2026/ 9/3/2026/ 10-09-2026 | L41: SEPTEMBER | M41: =H41-I41 -> 4595 | N41: SIGNED
A42: S18 | B42: LIZZIE NYAMBURA | C42: 0792838695 | E42: 10100 | F42: 315 | G42: =AUGUST!M42 -> 351 | H42: =D42+E42+G42+F42 -> 10766 | I42: =10315 -> 10315 | J42: UI16L4Y3KD | K42: 46266 | L42: SEPTEMBER | M42: =H42-I42 -> 451 | N42: SIGNED
A43: S19 | B43: JOSEPH NDUNG'U | C43: 0725823244 | E43: 10100 | F43: 180 | G43: =AUGUST!M43 -> 0 | H43: =D43+E43+G43+F43 -> 10280 | I43: =10280 -> 10280 | J43: UI2IJ4RLQO | K43: 9/2/2026 | L43: SEPTEMBER | M43: =H43-I43 -> 0 | N43: SIGNED
A44: S20 | B44: PHELISIA | C44: 0718117097 | E44: 10100 | F44: 675 | G44: =AUGUST!M44 -> 1729 | H44: =D44+E44+G44+F44 -> 12504 | I44: =11000 -> 11000 | J44: UIB2T5YYMF | K44: 9/11/2026 | L44: SEPTEMBER | M44: =H44-I44 -> 1504 | N44: SIGNED
A45: S21 | B45: JOEL MAINA | C45: 0797262139 | E45: 10100 | F45: 300 | G45: =AUGUST!M45 -> -16230 | H45: =D45+E45+G45+F45 -> -5830 | I45: =10300 -> 10300 | J45: UIA0T6A83P | K45: 9/10/2026 | L45: SEPTEMBER | M45: =H45-I45 -> -16130 | N45: SIGNED
A46: S22 | B46: JONA KIBET | C46: 0790405201 | E46: 10100 | F46: 810 | G46: =AUGUST!M46 -> -111 | H46: =D46+E46+G46+F46 -> 10799 | I46: =10910 -> 10910 | J46: UI5QO52GIJ | K46: 46270 | L46: SEPTEMBER | M46: =H46-I46 -> -111 | N46: SIGNED
A47: S23 | B47: CINDY | C47: 0726239783 | E47: 10100 | F47: 180 | G47: =AUGUST!M47 -> 90 | H47: =D47+E47+G47+F47 -> 10370 | I47: =10280 -> 10280 | J47: UI9LX5J6TI | K47: 46274 | L47: SEPTEMBER | M47: =H47-I47 -> 90 | N47: SIGNED
A48: S24 | B48: YASHON | C48: 0711167127 | E48: 10100 | F48: 135 | G48: =AUGUST!M48 -> 100 | H48: =D48+E48+G48+F48 -> 10335 | I48: =10235 -> 10235 | J48: UI2I94UQ8Z | K48: 9/2/2026 | L48: SEPTEMBER | M48: =H48-I48 -> 100 | N48: SIGNED
A49: S25 | B49: LIZZIE | C49: 0706359132 | E49: 10100 | F49: 330 | G49: =AUGUST!M49 -> 175 | H49: =D49+E49+G49+F49 -> 10605 | I49: =10430 -> 10430 | J49: UI5U94NPN1 | K49: 9/5/2026 | L49: SEPTEMBER | M49: =H49-I49 -> 175 | N49: SIGNED
A50: S26 | B50: LUCY | C50: 0703357741 | E50: 10100 | F50: 15 | G50: =AUGUST!M50 -> -10 | H50: =D50+E50+G50+F50 -> 10105 | I50: =10115 -> 10115 | J50: UIA8569NKM | K50: 9/10/2026 | L50: SEPTEMBER | M50: =H50-I50 -> -10 | N50: SIGNED
A51: S27 | B51: DOROTHY | C51: 0793749115 | E51: 10100 | F51: 120 | G51: =AUGUST!M51 -> -40 | H51: =D51+E51+G51+F51 -> 10180 | I51: =10220 -> 10220 | J51: UI2B15B29P | K51: 46267 | L51: SEPTEMBER | M51: =H51-I51 -> -40 | N51: SIGNED
A52: S28 | B52: STELLA | C52: 0745586458 | E52: 10100 | F52: 315 | G52: =AUGUST!M52 -> -25555 | H52: =D52+E52+G52+F52 -> -15140 | I52: =10520 -> 10520 | J52: UI1DS56UCC | K52: 9/1/2026 | L52: SEPTEMBER | M52: =H52-I52 -> -25660 | N52: SIGNED
A53: S29 | B53: JUMA | C53: 0702146655 | E53: 10100 | F53: 540 | G53: =AUGUST!M53 -> 445 | H53: =D53+E53+G53+F53 -> 11085 | I53: =10640 -> 10640 | J53: UI1A25BNYC | K53: 46266 | L53: SEPTEMBER | M53: =H53-I53 -> 445 | N53: SIGNED
A54: S30 | B54: JOSEPH MUGO | C54: 0704339161 | E54: 10100 | F54: 450 | G54: =AUGUST!M54 -> -80 | H54: =D54+E54+G54+F54 -> 10470 | I54: =10550 -> 10550 | J54: UI5SB52NPM | K54: 46270 | L54: SEPTEMBER | M54: =H54-I54 -> -80 | N54: SIGNED
A55: S31 | B55: TIMOTHY KURIA | C55: 0797778633 | E55: 10100 | F55: 420 | G55: =AUGUST!M55 -> 100 | H55: =D55+E55+G55+F55 -> 10620 | I55: =10580 -> 10580 | J55: UI66C4X8RB | K55: 46271 | L55: SEPTEMBER | M55: =H55-I55 -> 40 | N55: SIGNED
A56: S32 | B56: MRENJE CHRISANTHUS | C56: 0794033100 | E56: 10100 | F56: 315 | G56: =AUGUST!M56 -> 540 | H56: =D56+E56+G56+F56 -> 10955 | I56: =10315 -> 10315 | J56: UI5BL5XXPQ | K56: 46270 | L56: SEPTEMBER | M56: =H56-I56 -> 640 | N56: SIGNED
A57: Totals | E57: =SUM(E9:E56) -> 480700 | F57: =SUM(F9:F56) -> 17550 | G57: =SUM(G9:G56) -> -55394 | H57: =SUM(H9:H56) -> 442856 | I57: =SUM(I9:I56) -> 489830 | M57: =SUM(M9:M56) -> -46974
A59: Deductions
A60: Less Management fees | I60: =6%*I57 -> 29389.8
A61: TOTAL DEDUCTIONS | I61: =SUM(I60:I60) -> 29389.8
A63: BAL B/F | I63: =JUNE!M64 -> 29273.1 | J63: Paid | L63: Paid | M63: Balance
A64: AMOUNT DUE | I64: =I61 -> 29389.8 | M64: =I64-J64-L64 -> 29389.8
A66: AUTHORISED BY JOSEPH GITHINJI | M66: 9/31/2026
E70: =I57/H57*100 -> 110.60706

Sheet OCTOBER
C1: LOBBY ENTERPRISES
A2: PROPERTY MANAGERS AND ESTATE AGENTS
A3: JULY 2026
J4: P.O.BOX 11987
A5: STUDIO HAVEN | J5: TEL : 0722711933/4454322
A6: A/C | I6: Care taker | J6: ELIZABETH
I7: Phone no | J7: 0796292019
A8: HSE NO | B8: NAME | C8: PHONE NO | D8: DEPOSIT PAID | E8: MONTHLY RENT | F8: WATER BILL | G8: BAL B/D | H8: RENT DUE | I8: RENT PAID | J8: RCT NO | K8: DATE | L8: PERIOD | M8: BALANCE | N8: FORMS | O8: STATUS
A9: H1 | B9: ROSE | C9: 0707714065 | E9: 10100 | F9: 570 | G9: =AUGUST!M9 -> 0 | H9: =D9+E9+G9+F9 -> 10670 | I9: =10655 -> 10655 | J9: UJ2HM8HXV3 | K9: 10/2/2026 | L9: OCTOBER | M9: =H9-I9 -> 15 | N9: SIGNED
A10: H2 | B10: BENSON | C10: 0741776284 | E10: 10100 | F10: 390 | G10: =AUGUST!M10 -> 55 | H10: =D10+E10+G10+F10 -> 10545 | L10: OCTOBER | M10: =H10-I10 -> 10545 | N10: SIGNED
A11: H3 | B11: TESSA MARRIE | C11: 0716507709 | E11: 10100 | F11: 180 | G11: =AUGUST!M11 -> 2010 | H11: =D11+E11+G11+F11 -> 12290 | L11: OCTOBER | M11: =H11-I11 -> 12290 | N11: SIGNED
A12: H4 | B12: JOY | C12: 0724674470 | E12: 10100 | F12: 255 | G12: =AUGUST!M12 -> -4645 | H12: =D12+E12+G12+F12 -> 5710 | L12: OCTOBER | M12: =H12-I12 -> 5710 | N12: SIGNED
A13: H5 | B13: PAUL | C13: 0723316248 | E13: 10100 | F13: 375 | G13: =AUGUST!M13 -> 14035 | H13: =D13+E13+G13+F13 -> 24510 | I13: =10000 -> 10000 | J13: UJ1OF8JRAR | K13: 10/1/2026 | L13: OCTOBER | M13: =H13-I13 -> 14510 | N13: SIGNED
A14: H6 | B14: MARY MESUSWA | C14: 0757079026 | E14: 10100 | F14: 300 | G14: =AUGUST!M14 -> 1080 | H14: =D14+E14+G14+F14 -> 11480 | I14: =10990 -> 10990 | J14: UJ2PY8CMOE | K14: 10/2/2026 | L14: OCTOBER | M14: =H14-I14 -> 490 | N14: SIGNED
A15: H7 | B15: MUNYIRI WACHIRA | C15: 0700935843 | E15: 10100 | F15: 165 | G15: =AUGUST!M15 -> 110 | H15: =D15+E15+G15+F15 -> 10375 | I15: =10000 -> 10000 | J15: UIML0712EZ | K15: 9/22/2026 | L15: OCTOBER | M15: =H15-I15 -> 375 | N15: SIGNED
A16: H8 | B16: BONIFACE | C16: 0703962575 | E16: 12100 | F16: 750 | G16: =AUGUST!M16 -> 601 | H16: =D16+E16+G16+F16 -> 13451 | L16: OCTOBER | M16: =H16-I16 -> 13451 | N16: SIGNED
A17: H9 | B17: ROBERT | C17: 0726405930 | E17: 14100 | F17: 1110 | G17: =AUGUST!M17 -> 3305 | H17: =D17+E17+G17+F17 -> 18515 | L17: OCTOBER | M17: =H17-I17 -> 18515 | N17: SIGNED
A18: H10 | B18: BEATRICE | C18: 0711729058 | E18: 10100 | F18: 765 | G18: =AUGUST!M18 -> 660 | H18: =D18+E18+G18+F18 -> 11525 | L18: OCTOBER | M18: =H18-I18 -> 11525 | N18: SIGNED
A19: H11 | B19: PETER | C19: 0708568404 | E19: 10100 | F19: 120 | G19: =AUGUST!M19 -> 105 | H19: =D19+E19+G19+F19 -> 10325 | I19: =10235 -> 10235 | J19: UJ2K88NPM9 | K19: 10/2/2026 | L19: OCTOBER | M19: =H19-I19 -> 90 | N19: SIGNED
A20: H12 | B20: DUNCAN CHERUIYOT | C20: 0708748835 | E20: 10100 | F20: 135 | G20: =AUGUST!M20 -> 5235 | H20: =D20+E20+G20+F20 -> 15470 | L20: OCTOBER | M20: =H20-I20 -> 15470 | N20: SIGNED
A21: H13 | B21: SHAWN RATEMO | C21: 0716484383/'0721832745 | E21: 10100 | F21: 420 | G21: =AUGUST!M21 -> 385 | H21: =D21+E21+G21+F21 -> 10905 | L21: OCTOBER | M21: =H21-I21 -> 10905 | N21: SIGNED
A22: H14 | B22: MOMANYI KENNEDY | C22: 0114982450 | E22: 10100 | F22: 900 | G22: =AUGUST!M22 -> -9445 | H22: =D22+E22+G22+F22 -> 1555 | L22: OCTOBER | M22: =H22-I22 -> 1555 | N22: SIGNED
A23: H15 | B23: RONO ELIJAH | C23: 0745935239 | E23: =10100 -> 10100 | F23: 780 | G23: =AUGUST!M23 -> -10985 | H23: =D23+E23+G23+F23 -> -105 | I23: =15800 -> 15800 | J23: UIP1F83840 | K23: 9/25/2026 | L23: OCTOBER | M23: =H23-I23 -> -15905 | N23: SIGNED
A24: H16 | B24: KELVIN GITONGA | C24: 0792391382 | E24: 10100 | F24: 555 | G24: =AUGUST!M24 -> -105 | H24: =D24+E24+G24+F24 -> 10550 | L24: OCTOBER | M24: =H24-I24 -> 10550 | N24: SIGNED
A25: S1 | B25: VIVIAN | C25: 0748596476 | E25: 10100 | F25: 495 | G25: =AUGUST!M25 -> 869 | H25: =D25+E25+G25+F25 -> 11464 | L25: OCTOBER | M25: =H25-I25 -> 11464 | N25: SIGNED
A26: S2 | B26: LINDA | C26: 0748689851 | E26: 10100 | F26: 150 | G26: =AUGUST!M26 -> 0 | H26: =D26+E26+G26+F26 -> 10250 | L26: OCTOBER | M26: =H26-I26 -> 10250 | N26: SIGNED
A27: S3 | B27: WARREN | C27: 0769883948 | E27: 10100 | F27: 510 | G27: =AUGUST!M27 -> -680 | H27: =D27+E27+G27+F27 -> 9930 | L27: OCTOBER | M27: =H27-I27 -> 9930 | N27: SIGNED
A28: S4 | B28: SCOLA | C28: 0793889379 | E28: 10100 | F28: 630 | G28: =AUGUST!M28 -> 1930 | H28: =D28+E28+G28+F28 -> 12660 | L28: OCTOBER | M28: =H28-I28 -> 12660 | N28: SIGNED
A29: S5 | B29: CARETAKER | F29: 0 | G29: =AUGUST!M29 -> 0 | H29: =D29+E29+G29+F29 -> 0 | L29: OCTOBER | M29: =H29-I29 -> 0 | N29: SIGNED
A30: S6 | B30: IMELDA | C30: 0723500330 | E30: 10100 | F30: 255 | G30: =AUGUST!M30 -> 155 | H30: =D30+E30+G30+F30 -> 10510 | I30: =10300 -> 10300 | J30: UJ12F8U6RM | K30: 10/1/2026 | L30: OCTOBER | M30: =H30-I30 -> 210 | N30: SIGNED
A31: S7 | B31: EVANS | C31: 0702377661 | E31: 10100 | F31: 30 | G31: =AUGUST!M31 -> -8 | H31: =D31+E31+G31+F31 -> 10122 | L31: OCTOBER | M31: =H31-I31 -> 10122 | N31: SIGNED
A32: S8 | B32: BRIAN CHERUIYOT | C32: 0746324500 | E32: 10100 | F32: 1110 | G32: =AUGUST!M32 -> 3540 | H32: =D32+E32+G32+F32 -> 14750 | L32: OCTOBER | M32: =H32-I32 -> 14750 | N32: SIGNED
A33: S9 | B33: DORCAS KENANDA | C33: 0723433108 | E33: 10100 | F33: 195 | G33: =AUGUST!M33 -> -155 | H33: =D33+E33+G33+F33 -> 10140 | I33: =10220 -> 10220 | J33: UJ3479OZ9B | K33: 10/3/2026 | L33: OCTOBER | M33: =H33-I33 -> -80 | N33: SIGNED
A34: S10 | B34: MONICAH | C34: 0740454928 | E34: 10100 | F34: 180 | G34: =AUGUST!M34 -> -10610 | H34: =D34+E34+G34+F34 -> -330 | L34: OCTOBER | M34: =H34-I34 -> -330 | N34: SIGNED
A35: S11 | B35: IAN KAMAU | C35: 0745292688 | E35: 10100 | F35: 135 | G35: =AUGUST!M35 -> -330 | H35: =D35+E35+G35+F35 -> 9905 | L35: OCTOBER | M35: =H35-I35 -> 9905 | N35: SIGNED
A36: S12 | B36: JUSTINE | C36: 0724282631 | E36: 10100 | F36: 45 | G36: =AUGUST!M36 -> -10095 | H36: =D36+E36+G36+F36 -> 50 | I36: =10150 -> 10150 | J36: 13RXP4YE2ZH | K36: 10/3/2026 | L36: OCTOBER | M36: =H36-I36 -> -10100 | N36: SIGNED
A37: S13 | B37: DERRICK | C37: 0707280087 | E37: 10100 | F37: 255 | G37: =AUGUST!M37 -> 35 | H37: =D37+E37+G37+F37 -> 10390 | L37: OCTOBER | M37: =H37-I37 -> 10390 | N37: SIGNED
A38: S14 | B38: VINCENT | C38: 0798467289 | E38: 10100 | F38: 300 | G38: =AUGUST!M38 -> 120 | H38: =D38+E38+G38+F38 -> 10520 | I38: =10655 -> 10655 | J38: UJ3198K7EX | K38: 10/3/2026 | L38: OCTOBER | M38: =H38-I38 -> -135 | N38: SIGNED
A39: S15 | B39: FRANCIS LOKITA | C39: 0706195266 | E39: 10100 | F39: 180 | G39: =AUGUST!M39 -> 0 | H39: =D39+E39+G39+F39 -> 10280 | L39: OCTOBER | M39: =H39-I39 -> 10280 | N39: SIGNED
A40: S16 | B40: BEN SAKWA | C40: 0725451845 | E40: 10100 | F40: 195 | G40: =AUGUST!M40 -> -10550 | H40: =D40+E40+G40+F40 -> -255 | L40: OCTOBER | M40: =H40-I40 -> -255 | N40: SIGNED
A41: S17 | B41: DENNIS OWINO | C41: 0712299080 | E41: 10100 | F41: 15 | G41: =AUGUST!M41 -> 6480 | H41: =D41+E41+G41+F41 -> 16595 | L41: OCTOBER | M41: =H41-I41 -> 16595 | N41: SIGNED | O41: 24TH
A42: S18 | B42: LIZZIE NYAMBURA | C42: 0792838695 | E42: 10100 | F42: 315 | G42: =AUGUST!M42 -> 351 | H42: =D42+E42+G42+F42 -> 10766 | I42: =10240 -> 10240 | J42: T3RY38KUA1S | K42: 10/3/2026 | L42: OCTOBER | M42: =H42-I42 -> 526 | N42: SIGNED
A43: S19 | B43: JOSEPH NDUNG'U | C43: 0725823244 | E43: 10100 | F43: 180 | G43: =AUGUST!M43 -> 0 | H43: =D43+E43+G43+F43 -> 10280 | I43: =10885+100 -> 10985 | J43: UJ2698OB0D / UJ3698OVQD | K43: 10/2/2026/ 10/3/2026 | L43: OCTOBER | M43: =H43-I43 -> -705 | N43: SIGNED
A44: S20 | B44: PHELISIA | C44: 0718117097 | E44: 10100 | F44: 675 | G44: =AUGUST!M44 -> 1729 | H44: =D44+E44+G44+F44 -> 12504 | L44: OCTOBER | M44: =H44-I44 -> 12504 | N44: SIGNED
A45: S21 | B45: JOEL MAINA | C45: 0797262139 | E45: 10100 | F45: 300 | G45: =AUGUST!M45 -> -16230 | H45: =D45+E45+G45+F45 -> -5830 | L45: OCTOBER | M45: =H45-I45 -> -5830 | N45: SIGNED
A46: S22 | B46: JONA KIBET | C46: 0790405201 | E46: 10100 | F46: 810 | G46: =AUGUST!M46 -> -111 | H46: =D46+E46+G46+F46 -> 10799 | L46: OCTOBER | M46: =H46-I46 -> 10799 | N46: SIGNED
A47: S23 | B47: CINDY | C47: 0726239783 | E47: 10100 | F47: 180 | G47: =AUGUST!M47 -> 90 | H47: =D47+E47+G47+F47 -> 10370 | L47: OCTOBER | M47: =H47-I47 -> 10370 | N47: SIGNED
A48: S24 | B48: YASHON | C48: 0711167127 | E48: 10100 | F48: 135 | G48: =AUGUST!M48 -> 100 | H48: =D48+E48+G48+F48 -> 10335 | L48: OCTOBER | M48: =H48-I48 -> 10335 | N48: SIGNED
A49: S25 | B49: LIZZIE | C49: 0706359132 | E49: 10100 | F49: 330 | G49: =AUGUST!M49 -> 175 | H49: =D49+E49+G49+F49 -> 10605 | L49: OCTOBER | M49: =H49-I49 -> 10605 | N49: SIGNED
A50: S26 | B50: LUCY | C50: 0703357741 | E50: 10100 | F50: 15 | G50: =AUGUST!M50 -> -10 | H50: =D50+E50+G50+F50 -> 10105 | L50: OCTOBER | M50: =H50-I50 -> 10105 | N50: SIGNED
A51: S27 | B51: DOROTHY | C51: 0793749115 | E51: 10100 | F51: 120 | G51: =AUGUST!M51 -> -40 | H51: =D51+E51+G51+F51 -> 10180 | I51: =10265 -> 10265 | J51: UJ3B18YDNL | K51: 10/3/2026 | L51: OCTOBER | M51: =H51-I51 -> -85 | N51: SIGNED
A52: S28 | B52: STELLA | C52: 0745586458 | E52: 10100 | F52: 315 | G52: =AUGUST!M52 -> -25555 | H52: =D52+E52+G52+F52 -> -15140 | I52: =10680 -> 10680 | J52: UJ2DS8YGUX | K52: 10/2/2026 | L52: OCTOBER | M52: =H52-I52 -> -25820 | N52: SIGNED
A53: S29 | B53: JUMA | C53: 0702146655 | E53: 10100 | F53: 540 | G53: =AUGUST!M53 -> 445 | H53: =D53+E53+G53+F53 -> 11085 | I53: =10580 -> 10580 | J53: UJ2A294HGD | K53: 10/2/2026 | L53: OCTOBER | M53: =H53-I53 -> 505 | N53: SIGNED
A54: S30 | B54: JOSEPH MUGO | C54: 0704339161 | E54: 10100 | F54: 450 | G54: =AUGUST!M54 -> -80 | H54: =D54+E54+G54+F54 -> 10470 | L54: OCTOBER | M54: =H54-I54 -> 10470 | N54: SIGNED
A55: S31 | B55: IVY AYOO | C55: 0748312457 | D55: 10000 | E55: 10100 | F55: 0 | G55: 0 | H55: =D55+E55+G55+F55 -> 20100 | I55: =20100 -> 20100 | J55: UIR7B804VT | K55: 9/27/2026 | L55: OCTOBER | M55: =H55-I55 -> 0 | N55: SIGNED | O55: NEW TENANT
A56: S32 | B56: MRENJE CHRISANTHUS | C56: 0794033100 | E56: 10100 | F56: 315 | G56: =AUGUST!M56 -> 540 | H56: =D56+E56+G56+F56 -> 10955 | I56: =10360 -> 10360 | J56: UJ5BL9M2J1 | K56: 10/5/2026 | L56: OCTOBER | M56: =H56-I56 -> 595 | N56: SIGNED
A57: Totals | E57: =SUM(E9:E56) -> 480700 | F57: =SUM(F9:F56) -> 17130 | G57: =SUM(G9:G56) -> -55494 | H57: =SUM(H9:H56) -> 452336 | I57: =SUM(I9:I56) -> 192215 | M57: =SUM(M9:M56) -> 260121
A59: Deductions
A60: Less Management fees | I60: =6%*I57 -> 11532.9
A61: TOTAL DEDUCTIONS | I61: =SUM(I60:I60) -> 11532.9
A63: BAL B/F | I63: =JUNE!M64 -> 29273.1 | J63: Paid | L63: Paid | M63: Balance
A64: AMOUNT DUE | I64: =I61 -> 11532.9 | M64: =I64-J64-L64 -> 11532.9
A66: AUTHORISED BY JOSEPH GITHINJI | M66: 46326
E70: =I57/H57*100 -> 42.493854
